Workbook

Sheet VENTES
C1: r | H1: valeur contrat av. taxes | I1: Valeur total | J1: upsell | K1: Chèques | L1: date de prod
B2: Téléphoniste | C2: nom du client | D2: montant versement | E2: Montant Chèque | F2: # contrat
B3: clem | C3: Valérie Morin | D3: 75.55 | F3: 962168 | G3: contrat envoyé | H3: =I3/1.14975 -> 219.03312 | I3: =D3/0.3 -> 251.83333
B4: Flavie | C4: Rita Amabili | D4: 90.49 | F4: 933529 | G4: contrat envoyé | H4: =I4/1.14975 -> 262.34689 | I4: =D4/0.3 -> 301.63333 | J4: 156.1 | L4: mi-mai
B5: Flavie | C5: Marie-Lou Allard | D5: 158.32 | G5: Envoyé | H5: =I5/1.14975 -> 458.99833 | I5: =D5/0.3 -> 527.73333 | J5: 210 | L5: Fin mai
B6: Will | C6: Josée Beauchesne | D6: 85.2 | F6: 908961 | G6: contrat envoyé | H6: =I6/1.14975 -> 247.01022 | I6: =D6/0.3 -> 284
B7: Flavie | C7: Denise Demers | D7: 103.2 | F7: 906704 | G7: contrat envoyé | H7: =I7/1.14975 -> 299.19548 | I7: =D7/0.3 -> 344
B8: Flavie | C8: Linda Langlois | D8: 104.79 | F8: 925679 | G8: contrat envoyé | H8: =I8/1.14975 -> 303.80518 | I8: =D8/0.3 -> 349.3 | J8: 135.81 | L8: Mi-mai
B9: Flavie | C9: Annie Sabourin | D9: 65.96 | F9: 945446 | G9: contrat envoyé | H9: =I9/1.14975 -> 191.22998 | I9: =D9/0.3 -> 219.86667
B10: Paul | C10: Maryse Desrochers | D10: Remboursement 134.88$ | F10: 139122 | G10: FAIT | H10: =I10/1.14975 -> #VALUE! | I10: =D10/0.3 -> #VALUE!
B11: Paul | C11: Louise Larivère | F11: 996900 | G11: contrat envoyé | H11: =I11/1.14975 -> 0 | I11: =D11/0.3 -> 0
B12: Will | C12: Sophie Martel | F12: 987427 | G12: contrat envoyé | H12: =I12/1.14975 -> 0 | I12: =D12/0.3 -> 0
B13: clem | C13: Serge Gagnon | D13: pas de dépot | F13: 919094 | H13: =I13/1.14975 -> #VALUE! | I13: =D13/0.3 -> #VALUE!
B14: clem | C14: Michel Spina | D14: pas de dépot | F14: 919094 | H14: =I14/1.14975 -> #VALUE! | I14: =D14/0.3 -> #VALUE!
B15: clem | C15: Pierre-Olivier Fiset | D15: 158.35 | F15: 950388 | H15: =I15/1.14975 -> 459.08531 | I15: =D15/0.3 -> 527.83333
B16: clem | C16: sylvie venne | D16: 71.71 | F16: 965188 | H16: =I16/1.14975 -> 207.90027 | I16: =D16/0.3 -> 239.03333
B17: clem | C17: Marie-France Pelland | D17: 104.34 | F17: 935661 | H17: =I17/1.14975 -> 302.50054 | I17: =D17/0.3 -> 347.8
B18: Flavie | C18: Robert H. Blackburn | D18: 113.82 | F18: 915634 | H18: =I18/1.14975 -> 329.98478 | I18: =D18/0.3 -> 379.4 | L18: Mi-mai
B19: Flavie | C19: France Rougeau | D19: 113.68 | F19: 996872 | H19: =I19/1.14975 -> 329.57889 | I19: =D19/0.3 -> 378.93333
B20: Flavie | C20: Michel Gilbert | D20: 248.25 | H20: =I20/1.14975 -> 719.72168 | I20: =D20/0.3 -> 827.5
B21: Teddy | C21: Monique Charrette | D21: 79.68 | F21: 928903 | H21: =I21/1.14975 -> 231.00674 | I21: =D21/0.3 -> 265.6
B22: Flavie | C22: Suzanne Allaire | D22: 175.91 | F22: 916040 | H22: =I22/1.14975 -> 509.99493 | I22: =D22/0.3 -> 586.36667 | L22: Fin-Mai
C23: Il y a 2 transactions pour Flavie au même numéro de contrat: 933529 | H23: =I23/1.14975 -> 0 | I23: =D23/0.3 -> 0
C24: 1-90.49$ | H24: =I24/1.14975 -> 0 | I24: =D24/0.3 -> 0
C25: 2-156.74$ | H25: =I25/1.14975 -> 0 | I25: =D25/0.3 -> 0
B26: Chloée | C26: Aida Daoud | D26: 154.27 | F26: 912140 | H26: =I26/1.14975 -> 447.25665 | I26: =D26/0.3 -> 514.23333
B27: Flavie | C27: Fabie Duhamel | D27: 147.02 | F27: 929309 | H27: =I27/1.14975 -> 426.23759 | I27: =D27/0.3 -> 490.06667
B28: teddy | C28: Louise wittebol | D28: 113.82 | F28: 922983 | H28: =I28/1.14975 -> 329.98478 | I28: =D28/0.3 -> 379.4
B29: Flavie | C29: Jacqueline Fauteux | D29: 97.32 | F29: 929309 | H29: =I29/1.14975 -> 282.14829 | I29: =D29/0.3 -> 324.4
B30: Jérémy | C30: Sylvie Maurissette | E30: 83.66 | F30: 959846 | H30: 242.55 | I30: =H30*1.14975 -> 278.87186
B31: Jérémy | C31: Veronique Moses
B32: Flavie | C32: Lucille Berthiaume | D32: 49.32 | F32: 945113 | H32: 142.98 | I32: 164.4 | L32: Fin-mai
B33: Chloée | C33: Benoit Martel | D33: 70,57$ | F33: 912870 | H33: 204.59 | I33: 235.23
B34: Flavien | C34: Veronique Rabel | D34: 132.80$ | F34: 991402 | H34: 385 | I34: 442.65$
B35: Chloée | C35: Francois Fontaine | D35: 44,54$ | F35: 949793 | H35: 129.14 | I35: 148.47 | L35: fin juin
B36: teddy | C36: Sylvain Angrignon | D36: 150.82 | F36: 969579 | H36: 437.25 | I36: 502.73 | L36: mi mai
B37: teddy | C37: Nathalie Malette | D37: 70.18 | F37: 961029 | H37: 203.5 | I37: 233.97 | L37: mi mai
B38: Flavie | C38: Solange Martin | D38: 98.4 | E38: virement | F38: 913339 | H38: 285.29 | I38: 328.01 | L38: Juin
B39: Flavie | C39: Josée Leduc | D39: 174.7 | F39: 991145 | H39: 506.5 | I39: 582.35 | L39: Juin
B40: Flavien | C40: Kim Ducharme | D40: 75.88$ | F40: 952276 | H40: 220 | I40: 252.95$ | L40: Debut juillet
B41: clem | C41: Nathalie et William côté | D41: 85,37$ | F41: 948060 | H41: 247.5 | I41: 284,56$ | L41: fin-mai
B42: Chloée | C42: Billy Borys | D42: 96,18$ | F42: 938422 | H42: 278.85 | I42: 320.68 | L42: mi-mai
B43: teddy | C43: Marie Claude Boucher | D43: 101.30 | F43: 928479 | H43: 293.67 | I43: 337.65 | L43: mi mai
B44: Flavie | C44: Hélene Tardif | D44: 161.7 | F44: 932751 | H44: 468.8 | I44: 539.00 | L44: Juin
B45: Flavie | C45: France Lafond | D45: 125.21 | F45: 933074 | H45: 363 | I45: 417.36
H46: =SUM(H32:H45) -> 4166.07
B47: Flavie | C47: Jaqueline Chagnon | D47: 72.09 | F47: 940320 | H47: 209 | I47: 240.30 | L47: Juin
B48: Flavien | C48: Julie Michaud | D48: 34.15$ | F48: 968444 | H48: 99 | I48: 113.83$ | L48: Debut Mai
B49: Teddy | C49: Maurice abergel | D49: 76.63 | F49: 955068 | H49: 222 | I49: 255.47
B50: Chloée | C50: Collen Carroll | D50: 54,07$ | F50: 934865 | H50: 156.75 | I50: 180,22$ | L50: juin
B51: teddy | C51: Tamara Kradephol | D51: 66.59 | F51: 971250 | H51: 193.05 | I51: 221.96 | L51: mi mai
B52: Flavien | C52: Patrice Meloche | D52: 75.88$ | F52: 941244 | H52: 220 | I52: 252.95$ | L52: juin
B53: Flavie | C53: Louis Aubé | D53: Virement Interac en attente | H53: 1009.2 | I53: 1160,39$ | L53: mi-mai
B54: Chloée | C54: Mary Brown | D54: 73,99$ | F54: 964626 | H54: 214.5 | I54: 246.62$ | L54: Fin mai
B55: teddy | C55: Jacques Tremblay | D55: 136.08 | F55: 985637 | H55: 394.52 | I55: 453.59 | L55: DEBUTMAI
B56: Flavie | C56: Hugette Laperle | D56: 68.30 | F56: 979222 | H56: 198 | I56: 227.65 | L56: Juin
B57: teddy | C57: Donna Farnworth | D57: 187.43 | F57: 904243 | H57: 543.13 | I57: 624.46 | L57: mi mai
B58: Chloée | C58: Yves Houle | D58: 56.91 | F58: 986964 | H58: 165 | I58: 189.71 | L58: juin
B59: clem | C59: Pascale Brillon | D59: 85.37 | F59: 920826 | H59: 122.5 | I59: 140.84 | L59: début juin
B60: Flavien | C60: Nicole Lemay | D60: 170.23$ | F60: 914071 | H60: 493.52 | I60: 567.43$ | J60: 195.00$ | L60: Fin Juin
H61: =SUM(H47:H60) -> 4240.17
B62: teddy | C62: monique jolicoeur | D62: 90.29 | F62: 993265 | H62: 261.77 | I62: 300.97 | L62: mi mai
B63: Chloée | C63: Jean thomas Courchesne | D63: $79.68 | F63: 995367 | H63: 231 | I63: 265.59 | L63: juin
B64: Chloée | C64: Elizabeth Duncan | D64: $113.81 | F64: 980963 | H64: 329.97 | I64: 378.38 | L64: juin
B65: Chloée | C65: Esther Viens | D65: $149.87 | F65: 969430 | H65: 434.5 | I65: 499.57 | L65: juin
B66: teddy | C66: Kzleza Jeric Karmela | D66: 76.45 | F66: 998335 | H66: 221.65 | I66: 254.84
B67: teddy | C67: David Plummer | D67: 107.00 | F67: 948139 | H67: 310.2 | I67: 356.65 | L67: mi mai
B68: teddy | C68: Annebel Soutar | D68: 65.83 | F68: 948139 | H68: 190.85 | I68: 219.43 | L68: juin
B69: paul | C69: mireille tremblay | D69: 73.99 | F69: 936502 | H69: 214.5 | I69: 246.52
B70: paul | C70: Paulette girard | D70: 30.35 | F70: 920464 | H70: 88 | I70: 101.18
B71: paul | C71: Marise desrochers | D71: 134.88 | F71: 933140 | H71: 434.5 | I71: 499.56
B72: paul | C72: Louise lariviere | D72: 115.63 | F72: 996900 | H72: 335.23 | I72: 385.43
H73: =SUM(H62:H72) -> 3052.17
B74: Flavien | C74: Julie Michaud (a decide de renouveller par carte finalement non par interac) | D74: 34.15$ | F74: 995104 | H74: 90 | I74: 113.83$ | L74: debut juin
B75: Flavien | C75: Nathalie Boivin (virement interac) | D75: 56.91$ | F75: 900216 | H75: 165 | I75: 189.71$ | L75: debut juin
B76: Flavien | C76: Zoe Perras | D76: 64.50$ | F76: 994134 | H76: 187 | I76: 215.00$ | L76: debut juin
B77: clem | C77: luc arbour | D77: pas de dépot | F77: 929829 | H77: 209 | I77: 240,30$ | L77: début juin
B78: clem | C78: Jean Laliberté | D78: 123.31 | F78: 945544 | H78: 357.5 | I78: 411,04$ | L78: MAI LE PLUS TÔT POSSIBLE
B79: clem | C79: Peter Gavas | D79: 89,16$ | F79: 993412 | H79: 258.49 | I79: 297,20$ | L79: DÉBUT MAI gouttières à l'automne
B80: clem | C80: Gaetan Guillemette | D80: 64,86$ | F80: 928311 | H80: 188.03 | I80: 216,19$ | L80: MAI LE PLUS TÔT POSSIBLE
B81: Flavien | C81: Chantal Demers | D81: 79.68$ | F81: 939064 | H81: 231 | I81: 265.59$ | L81: Debut Mai
B82: Flavien | C82: Sophie Bernard | D82: 91.06$ | F82: 945954 | H82: 264 | I82: 303.53$ | L82: debut mai
B83: clem | C83: lise desroches | D83: 69,92$ | F83: 901045 | H83: 202.7 | I83: 233,06$ | L83: debut mai
B84: Paul | C84: Suzanne Rondeau | D84: 58.9 | F84: 932092 | H84: 170.78 | I84: $196.35 | L84: Juin
B85: Paul | C85: Richard Brissette | D85: $88.31 | F85: 998863 | H85: 256.01 | I85: $294.35 | L85: Juin
B86: paul | C86: Lucie Turcotte | D86: $51.18 | F86: 908095 | H86: 148.39 | I86: $170.61 | L86: Juin
B87: clem | C87: Myriam Campagna | D87: 111,62$ | F87: 911271 | H87: 323.6 | I87: 372,06$ | L87: juin
B88: kev | C88: Gilles Tanguay | D88: $111,93 | E88: intérac | F88: 972802 | H88: 324.5 | I88: 373.09
B89: Paul | C89: Helene Flamand | D89: 68.30 | F89: 940368 | H89: 198 | I89: 227.65 | L89: A partir de mai
H90: =SUM(H74:H89) -> 3574
B91: clem | C91: Francine Trudeau | D91: 169,41$ | F91: 946874 | H91: 491.15 | I91: 564,70$ | L91: début juin
B92: amanda | C92: Denise Bellerose | D92: 116.6 | E92: interac | F92: 996737 | H92: 338.06 | I92: 388,68$ | L92: juin
B93: clem | C93: Hassan Hanano | D93: 161.56 | F93: 959836 | H93: 468.38 | I93: 538,52$ | L93: fin mai, début juin
H94: =SUM(H91:H93) -> 1297.59
B95: Paul | C95: Lauraine Begin | D95: 67.7 | F95: 987651 | H95: 181.78 | I95: 209 | L95: Mai
B96: Flavie | C96: Nancy Audet | D96: 142.28$ | E96: Interac | F96: 942885 | H96: 412.5 | I96: 474.27 | L96: fin mai
B97: Chloée | C97: Marie Josée Queenton | D97: 118.38$ | F97: 919460 | H97: 343.2 | I97: 394.59$ | L97: Juin
B98: clem | C98: Jacinthe Marleau | D98: 87,65$ | E98: interac | F98: 915369 | H98: 254.98 | I98: 293.16$ | L98: dernière de mai ou première de juin
B99: Flavie | C99: Andrée Mineau | D99: 26.82 | F99: 942885 | H99: =I99/1.14975 -> 77.756034 | I99: =D99/0.3 -> 89.4 | L99: juin
B100: Paul | C100: Charle Fortier | D100: 85.37 | F100: 950197 | H100: 275 | I100: =275*1.14975 -> 316.18125 | L100: Mai
...

Sheet VENTE EMILE
B1: Émile | C1: Marie Laberge | D1: 76.96 | E1: Crédit | F1: 976398 | H1: 223,16$ | I1: 256,54$
B2: Émile | C2: Constance Lamarche | D2: 86.15 | E2: Crédit | F2: 965965 | H2: 249,75$ | I2: 287,15$
B3: Émile | C3: Léonce Lavoie | D3: 44.15 | E3: Crédit | F3: 928308 | H3: 128$ | I3: 147,17$
B4: Émile | C4: Françoise Dumasivret | D4: 33.63 | E4: Crédit | F4: 918076 | H4: 97,5$ | I4: 112,10$
A5: 43927 | B5: Émile | C5: Alain Trudel | D5: 72.09 | E5: Virement | F5: 910235 | G5: 1er juin | H5: 209$ | I5: 240,30$
B6: Émile | C6: Mme Nancy | D6: 256.97 | E6: Virement | F6: 913619 | H6: 745$ | I6: 856,56$
B7: Émile | C7: Sylviane Legault | D7: 105.2 | E7: Crédit | F7: 916048 | H7: 305$ | I7: 350,67$
A8: 43928 | B8: Émile | C8: Yvon Aubut | D8: 68.98 | E8: Crédit | F8: 943736 | H8: 200$ | I8: 229,95$
B9: Émile | C9: Sébastien Morissette | D9: 154.7 | E9: Virement | F9: 974932 | H9: 448,5$ | I9: 515,66$
B10: Émile | C10: Sarah Barron | D10: 34.49 | E10: Crédit | F10: 970401 | H10: 100$ | I10: 114,98$
A11: 43929 | B11: Émile | C11: Louis De Repentigny | D11: 104.68 | E11: Crédit | F11: 940666 | G11: 1ère sem.juin | H11: 303.5 | I11: 348.95
B12: Émile | C12: François Simard | D12: 59.95 | E12: Crédit | F12: 952200 | H12: 173.82 | I12: 199.85
B13: Émile | C13: Michelle Leblanc | D13: 33.46 | E13: Crédit | F13: 978623 | H13: 97 | I13: 111.53
A14: 43930 | B14: Émile | C14: Heidi Garand | D14: 33.54 | E14: Crédit | F14: 913984 | H14: 97.5 | I14: 111.81
A15: 43931 | B15: Émile | C15: Louise-Andrée Bertrand | D15: 97.96 | E15: Crédit | F15: 912021 | G15: Lavage Automne | H15: 284 | I15: 326.53
B16: Émile | C16: Gabrielle Gauthier | D16: 62.09 | E16: Crédit | F16: 914164 | H16: 180 | I16: 206.96
B17: Émile | C17: Lisa Black | D17: 86.23 | E17: Crédit | F17: 902576 | H17: 250 | I17: 287.44
B18: Émile | C18: Claude Beaudoin | D18: 55.19 | E18: Crédit | F18: 926897 | H18: 160 | I18: 183.96
A20: 43932 | B20: Émile | C20: Hugues Tousignant | D20: 67.26 | E20: Crédit | F20: 905487 | H20: 195 | I20: 224.2
B21: Émile | C21: Joan Paiement | D21: 175.91 | E21: Crédit | F21: 999717 | H21: 510 | I21: 586.37
B22: Émile | C22: Élyse Laporte | D22: 112.27 | E22: Virement | F22: 966822 | H22: 325.5 | I22: 374.24
A23: 43933 | B23: Émile | C23: Nicolas Gagnon | D23: 222.99 | E23: Crédit | F23: 995072 | H23: 646.5 | I23: 743.31
D25: 646

Sheet VENTE ADRIEN
B1: Nom | C1: Dépôt | D1: Méthode | E1: Total | G1: Année client
A2: 43924 | B2: Martin Bureau | C2: 164.53 | D2: Crédit | E2: =C2/0.3/1.14975 -> 477.00225 | F2: 964899 | G2: 2017
B3: Michael Paradis Gaudette | C3: 172.81 | D3: Crédit | E3: =C3/0.3/1.14975 -> 501.00747 | F3: 942197 | G3: 2017
B4: Marie Eva De Villers | C4: 222.48 | D4: Crédit | E4: =C4/0.3/1.14975 -> 645.00978 | F4: 988324 | G4: 2017
B5: Éric Cadotte | C5: 210.4 | D5: Crédit | E5: =C5/0.3/1.14975 -> 609.98768 | F5: ok | G5: 2019
B6: Dominique Houle | C6: 86.92 | D6: Crédit | E6: =C6/0.3/1.14975 -> 251.99681 | F6: 979732 | G6: 2019
B7: Michelle St-Pierre | C7: 101.75 | D7: Crédit | E7: =C7/0.3/1.14975 -> 294.99166 | F7: 945662 | G7: 2017
B8: Kathryn Pryce | C8: 114.52 | D8: Crédit | E8: =C8/0.3/1.14975 -> 332.01421 | G8: 2017
B9: Ann Beer | C9: 169.98 | D9: Crédit | E9: =C9/0.3/1.14975 -> 492.80278 | G9: 2019
B10: Marie-Chantale Berube | C10: 136.25 | D10: Crédit | E10: =C10/0.3/1.14975 -> 395.01341 | F10: 912483 | G10: 2019
B11: Yves Lewis | C11: 98.48 | D11: Crédit | E11: =C11/0.3/1.14975 -> 285.51134 | G11: 2017
B12: Kathryn Greenaway | C12: 77.61 | D12: Crédit | E12: =C12/0.3/1.14975 -> 225.00544 | G12: 2019
A14: 43928 | B14: Debra Farrell | C14: 169.01 | D14: Crédit | E14: =C14/0.3/1.14975 -> 489.99058 | F14: 908031 | G14: 2013-2014
A16: 43931 | B16: Veronica Henry | C16: 39.67 | D16: Crédit | E16: =C16/0.3/1.14975 -> 115.01051 | F16: 936735 | G16: Online 2019
B17: David Oneill | C17: 53.46 | D17: Chèque | E17: =C17/0.3/1.14975 -> 154.99022 | F17: 906268 | G17: 2013-2014
B18: Djazia Bensalem | C18: 29.84 | D18: Crédit | E18: =C18/0.3/1.14975 -> 86.51156 | F18: 961959 | G18: Online 2019
B19: Suzan McNamara | C19: 62.09 | D19: Crédit | E19: =C19/0.3/1.14975 -> 180.01015 | F19: 964922 | G19: Online 2019
B20: Renée Brousseau | C20: 110.03 | D20: Yohan 2019 approuvé | E20: =C20/0.3/1.14975 -> 318.99688 | F20: 933858 | G20: 2019
B21: Lise Gendron | C21: 46.39 | D21: Crédit | E21: =C21/0.3/1.14975 -> 134.49301 | F21: 969508 | G21: Online 2019
A23: 43932 | B23: Lina Fang | C23: 51.74 | D23: Fred 2019 approuvé | E23: =C23/0.3/1.14975 -> 150.00362 | F23: 906427 | G23: 2019
B24: Pascal Girard | C24: 51.74 | D24: Nicols Girard 2019 | E24: =C24/0.3/1.14975 -> 150.00362 | F24: 935482 | G24: 2019
B25: Pierre-Luc Bouchard | C25: 39.67 | D25: Crédit | E25: =C25/0.3/1.14975 -> 115.01051 | F25: 938377 | G25: Haie 2018
B26: Stephane Mongeau | C26: 132.8 | D26: Crédit | E26: =C26/0.3/1.14975 -> 385.01123 | F26: 953587 | G26: 2019
B27: Louise Lambert | C27: 153.49 | D27: Crédit | E27: =C27/0.3/1.14975 -> 444.99529 | F27: 997423 | G27: 2017
B28: Dany Lescault | C28: 242.22 | D28: Crédit | E28: =C28/0.3/1.14975 -> 702.23962 | F28: 912198 | G28: 2019
B29: Marie Leveille | C29: 40.36 | D29: Crédit | E29: =C29/0.3/1.14975 -> 117.01094 | F29: 940764 | G29: 2018
A31: 43934 | B31: Julie Grenier | C31: 106.93 | D31: Crédit | E31: =C31/0.3/1.14975 -> 310.00942 | F31: 923255 | G31: Online 2019
B32: Isabelle Leblond | C32: 77.61 | D32: Crédit | E32: =C32/0.3/1.14975 -> 225.00544 | F32: 941031 | G32: 2019
B33: Danielle Corbeil | C33: 136.25 | D33: Chèque | E33: =C33/0.3/1.14975 -> 395.01341 | F33: 905625 | G33: 2017
B34: Isabelle Lagace | C34: 129.35 | D34: Crédit | E34: =C34/0.3/1.14975 -> 375.00906 | F34: 917462 | G34: 2019
B35: Johanne Cyr | C35: 25.18 | D35: Crédit | E35: =C35/0.3/1.14975 -> 73.001377 | F35: 961317 | G35: Online 2019
B36: Annie Gascon | C36: 67.26 | D36: Crédit | E36: =C36/0.3/1.14975 -> 194.99891 | F36: 908320 | G36: Haies GO
B37: Chantale Couture | C37: 136.25 | D37: Crédit | E37: =C37/0.3/1.14975 -> 395.01341 | F37: 918736 | G37: Online 2019
B38: Jacqueline Cote | C38: 82.78 | D38: Crédit | E38: =C38/0.3/1.14975 -> 239.9942 | F38: 935606 | G38: 2019
A40: 43935 | B40: Andre Cote | C40: 28.46 | D40: Crédit | E40: =C40/0.3/1.14975 -> 82.510691 | F40: 904478 | G40: 2019
B41: Susan Tremblay | C41: 60.36 | D41: Crédit | E41: =C41/0.3/1.14975 -> 174.99456 | F41: 967943 | G41: 2019
B42: Marie Helene Dufour | C42: 38.63 | D42: Crédit | E42: =C42/0.3/1.14975 -> 111.99536 | F42: 923490 | G42: 2017
B43: Café du vieux beloeil inc | C43: 163.36 | D43: Crédit | E43: =C43/0.3/1.14975 -> 473.61021 | F43: 983490 | G43: 2019
B44: Chantal Contant | C44: 98.3 | D44: Crédit | E44: =C44/0.3/1.14975 -> 284.98949 | F44: 994980 | G44: 2019
B45: Manon Boisrond | C45: 54.33 | D45: Crédit | E45: =C45/0.3/1.14975 -> 157.5125 | F45: 927339 | G45: 2018
B46: Alain Thauvette | C46: 113.83 | D46: Crédit | E46: =C46/0.3/1.14975 -> 330.01377 | F46: 953772 | G46: 2019
B47: Carmelo Bonadonna | C47: 100.03 | D47: Contrat 2019 Kevin | E47: =C47/0.3/1.14975 -> 290.00507 | F47: 915409 | G47: 2019
B48: Sabrina Laforge | C48: 43.13 | D48: Contrat 2019 Nicols G | E48: =C48/0.3/1.14975 -> 125.04168 | F48: 921039 | G48: 2019
B49: Marc Tanguay (voisin Marie-Helene Dufour) | C49: 37.86 | D49: Crédit | E49: =C49/0.3/1.14975 -> 109.76299 | F49: 919505 | G49: Référence
B50: Shawn Mandel | C50: 150.04 | D50: Contrat 2018 gouttieres | E50: =C50/0.3/1.14975 -> 434.99311 | F50: 966186 | G50: 2019
B51: Rolly Badra | C51: 120.72 | D51: Contrat fred 2019 | E51: =C51/0.3/1.14975 -> 349.98913 | F51: 962858 | G51: 2019
A53: 43936 | B53: Martin Sanfacon | C53: 45.53 | D53: Crédit | E53: =C53/0.3/1.14975 -> 131.99971 | F53: 905409 | G53: 2019
B54: Julie Le Vallee | C54: 89.16 | D54: Crédit | E54: =C54/0.3/1.14975 -> 258.49098 | F54: 981264 | G54: 2017
B55: Marie-Christine Veilleux | C55: 169.01 | D55: Crédit | E55: =C55/0.3/1.14975 -> 489.99058 | F55: 924284 | G55: 2017
B56: Tattiana Sragar | C56: 94.85 | D56: Jamais donné dépôt | E56: =C56/0.3/1.14975 -> 274.98732 | F56: 974273 | G56: 2016
A58: 43937 | B58: Cara Subirana | C58: 90.54 | D58: Crédit | E58: =C58/0.3/1.14975 -> 262.49185 | F58: 953981 | G58: 2017
B59: Marie-Claude Gilbert | C59: 205.23 | D59: Crédit | E59: =C59/0.3/1.14975 -> 594.99891 | F59: 972297 | G59: 2019
B60: Christiane Sarrazin | C60: 81.06 | D60: Crédit | E60: =C60/0.3/1.14975 -> 235.00761 | F60: 989476 | G60: 2019
B61: Josée Landry | C61: 44.84 | D61: Crédit | E61: =C61/0.3/1.14975 -> 129.99928 | F61: 991600 | G61: 2018
B62: Frédéric Tousignant | C62: 60.36 | D62: Crédit | E62: =C62/0.3/1.14975 -> 174.99456 | F62: 965799 | G62: 2016
B63: Michel Bonenfant | C63: 81.06 | D63: Crédit | E63: =C63/0.3/1.14975 -> 235.00761 | F63: 922356 | G63: 2016
A65: 43938 | B65: Katalin Toth | C65: 86.23 | D65: Crédit | E65: =C65/0.3/1.14975 -> 249.99638 | F65: 928405 | G65: 2016
B66: Céline Fontaine | C66: 32.77 | D66: Crédit | E66: =C66/0.3/1.14975 -> 95.006161 | F66: 948872 | G66: 2016
B67: Marie-Christine Veilleux | C67: =40*1.1497*0.3 -> 13.7964 | D67: Ajout contrat | E67: =C67/0.3/1.14975 -> 39.99826 | F67: 924284 | G67: 2017
B68: Pascale Chimi | C68: 131.07 | D68: Crédit | E68: =C68/0.3/1.14975 -> 379.99565 | F68: 923993 | G68: Online 2019
B69: Sonia Tremblay | C69: 112.1 | D69: Crédit | E69: =C69/0.3/1.14975 -> 324.99819 | F69: 912700 | G69: 2014
B70: Yves Daniel | C70: 137.97 | D70: Crédit | E70: =C70/0.3/1.14975 -> 400 | F70: 955463 | G70: 2018
B71: Anne Painchaud | C71: 235.93 | D71: Crédit | E71: =C71/0.3/1.14975 -> 684.00377 | F71: 977523 | G71: Online 2019
B72: Liliana Cruz | C72: 244.9 | D72: Crédit | E72: =C72/0.3/1.14975 -> 710.00942 | F72: 907655 | G72: 2018
B73: Diane Brunelle | C73: 73.12 | D73: Crédit | E73: =C73/0.3/1.14975 -> 211.98811 | F73: 919316 | G73: Online 2019
B74: Lena Labonte | C74: 43.12 | D74: Crédit | E74: =C74/0.3/1.14975 -> 125.01268 | F74: 973290 | G74: 2016
A76: 43939 | B76: Nathalie Bureau | C76: 114.86 | D76: Crédit | E76: =C76/0.3/1.14975 -> 332.99993 | F76: 977084 | G76: 2019
B77: Manon St-Onge | C77: 181.6 | D77: Crédit | E77: =C77/0.3/1.14975 -> 526.49127 | F77: 942314 | G77: 2016
B78: Patricia Labrie | C78: 67.26 | D78: Virement interac | E78: =C78/0.3/1.14975 -> 194.99891 | F78: 941649 | G78: 2016
B79: Reuben Schwartzman | C79: 153.49 | D79: Crédit | E79: =C79/0.3/1.14975 -> 444.99529 | F79: 962468 | G79: 2016
B80: Jane Leduc | C80: 198.5 | D80: Crédit | E80: =C80/0.3/1.14975 -> 575.48742 | F80: 912696 | G80: 2016
B81: Marc-Andre Grave | C81: 422.53 | D81: Crédit | E81: =C81/0.3/1.14975 -> 1224.9909 | F81: 980104 | G81: 2019
A83: 43940 | B83: Paulo | C83: 146.59 | D83: Crédit | E83: =C83/0.3/1.14975 -> 424.99094 | F83: 964336 | G83: 2017
A85: 43941 | B85: Marcoux Béatrice | C85: 154.81 | D85: Crédit | E85: =C85/0.3/1.14975 -> 448.82221 | F85: 954907 | G85: 2019
B86: Louise Roy | C86: 94.85 | D86: Crédit | E86: =C86/0.3/1.14975 -> 274.98732 | F86: 944660 | G86: 2018
B87: Charles fortier | C87: 332.85 | D87: Crédit | E87: =C87/0.3/1.14975 -> 964.99239 | F87: 962178 | G87: Référence
B88: Dominique Germain | C88: 51.57 | D88: Crédit | E88: =C88/0.3/1.14975 -> 149.51076 | F88: 981942 | G88: 2019
B89: Mylene Genot | C89: 93.34 | D89: Crédit | E89: =C89/0.3/1.14975 -> 270.60955 | F89: 933575 | G89: 2019
B90: Fannie Pelletier | C90: 301.81 | D90: Crédit | E90: =C90/0.3/1.14975 -> 875.00181 | F90: 977487 | G90: 2019
B91: Hopital Veterinaire Chambly | C91: 192.78 | D91: Virement entreprise | E91: =C91/0.3/1.14975 -> 558.90411 | F91: 936863 | G91: 2019
B92: Roger Baroumi | C92: 120.72 | D92: Crédit + GO Forfait | E92: =C92/0.3/1.14975 -> 349.98913 | F92: 958969 | G92: GO Forfait
A94: 43942

Sheet VENTE VINCENT
A1: date | B1: Client | C1: Valeur dépot | D1: Type paiement | E1: #contrat | F1: valeur contrat | G1: upsell | H1: date production
A2: 43924 | B2: Josée Ducharme | C2: 232.82 | D2: Crédit | E2: 984546 | F2: 675 | H2: Mi-Juin
A3: 43933 | B3: Guillaume Clément | C3: 41.39 | D3: Crédit | E3: 908006 | F3: 120 | H3: Mi-Juin
A4: 43935 | B4: Momodu Koridou Abdu | C4: 110.38 | D4: Virement | E4: 916500 | F4: 320 | H4: Mi-Juin
A5: 43940 | B5: Yves Desjardins | C5: 52.77 | D5: Crédit | E5: 905051 | F5: 153 | H5: Mi-Juin
A6: 43941 | B6: Isabelle Bouchard | C6: 124.77 | D6: Crédit | F6: 360 | H6: debut-juin

Sheet VENTE KEVIN
A1: date | B1: Client | C1: Valeur dépot | D1: Type paiement | E1: #contrat | F1: valeur contrat | G1: upsell | H1: date production

Sheet VENTE JOEL
A1: date | B1: Client | C1: Valeur dépot | D1: Type paiement | E1: #contrat | F1: valeur contrat | G1: upsell | H1: date production

Sheet VENTE JS
A1: date | B1: Client | C1: Valeur dépot | D1: Type paiement | E1: #contrat | F1: valeur contrat | G1: upsell | H1: date production
A2: 43938 | B2: Cinthia Lacharité | C2: 91.43 | D2: Credit | E2: 960695 | F2: 265 | G2: non | H2: Juin et septembre
A3: 43940 | B3: Madeleine Marchand | C3: 60.36 | D3: Credit | E3: 976792 | F3: 175 | G3: non | H3: Fin Juin
A4: 43940 | B4: Annie Bernier | C4: 79.33 | D4: Credit | E4: 986775 | F4: 230 | G4: non | H4: Fin Juin

Sheet VENTE JS LEBOEUF
A1: date | B1: Client | C1: Valeur dépot | D1: Type paiement | E1: #contrat | F1: valeur contrat | G1: upsell | H1: date production
A2: c'est ici toi lets go
A3: 2020-04-18 Éric Veilleux 0.00 940007 150.00 non Début Juin Pas content, pris 3 mois avant d'avoir service an passé, veut pas dépôt
A4: 2020-04-18 Brigitte Martin 0.00 955631 400.00 Mi-Juin 1 duplex, rappeler demain pour dépôt 514 639-4337
A6: 2020-04-20 Frederic Soares 143,21 clover 977724 416 Début Juin Clover téléphoniste, contrat dans RG perso

Sheet VENTE KENNY
A2: date | B2: Client | C2: Valeur dépot | D2: Type paiement | E2: #contrat | G2: Valeur contrat | H2: Valeur aprés taxes | I2: Upsell | K2: Date de rappel production
A3: 03-19 | B3: Suzanne Thérien | C3: Aucun dépot | E3: 934039 | G3: 142.56 | H3: 163.91 | K3: Juin
A4: 03-19 | B4: Lucie Roy | C4: Aucun dépot | E4: 988210 | G4: 154 | H4: 177.06 | K4: Juin
A5: 03-19 | B5: Cédric bélanger | C5: 73.35 | D5: crédit | E5: 932207 | G5: 212.66 | H5: 244.51 | K5: Juin
A6: 03-19 | B6: Gregory Jeannot | C6: 118.95 | D6: crédit | E6: 909712 | G6: 344.85 | H6: 396.49 | K6: Juin
A7: 03-19 | B7: Isabelle Dion | C7: 77.78 | D7: Virement | E7: 927572 | G7: 225.5 | H7: 259.27 | K7: Juin
A8: 03-19 | B8: Isabelle Roy Gregoire | C8: 312.73 | D8: crédit | E8: 962520 | G8: 906.68 | H8: 1042.45 | K8: Juin
B9: Jerome Jolicoeur | C9: 125.92 | D9: Virement | E9: 962559 | G9: 365.06 | H9: 419.73 | K9: Juin
B10: Luc Desgagnes | C10: 110.30 | D10: crédit | E10: 935247 | G10: 319.77 | H10: 367.66 | K10: Juin
B11: Odette Roy | C11: 50.46 | D11: crédit | E11: 926866 | G11: 146.3 | H11: 168.21 | K11: Juin
A13: 03-19 | B13: Patrice Poisson | C13: 103.01 | D13: crédit | E13: 995042 | G13: 298.65 | H13: 343.38 | K13: Juin
A14: 03-19 | B14: Véronique Delisle | C14: 47.65 | D14: Virement | E14: 908531 | G14: 138.15 | H14: 158.84 | K14: Juin
A15: 03-19 | B15: Stephane Vaillancourt | C15: 126.35$ | D15: Virement | E15: 903560 | G15: 366.3 | H15: 421.15$ | K15: Il veut un rdv le 13 Juin
A16: 03-19 | B16: Stephane lasselle | C16: 169.03 | D16: Virement | E16: 994736 | G16: 490.05 | H16: 563.43$ | K16: Juin
B17: Angeline lhérisson | C17: 49.32 | D17: virement | E17: 966311 | G17: 143 | H17: 164.41 | K17: Juin
A20: 03-22 | B20: Adel Karama | C20: 150.25 | D20: Virement | E20: 982764 | G20: 435.6 | H20: 500.83 | K20: mi juin- fin juin
B21: Ariane laliberté | C21: 106.33 | D21: credit | E21: 945239 | G21: 308.27 | H21: 354.44
B22: Mark Winkler | C22: 78.35 | D22: Crédit | E22: 907453 | G22: 227.15 | H22: 261.17
B23: Nathalie Juteau | C23: 102.45 | D23: Virement | E23: 963161 | G23: 297.01 | H23: 341.49 | K23: veut rdv le 13 juin
B24: andré Charrière | C24: 62.66 | D24: Cheque | E24: 913454 | G24: 181.67 | H24: 208.87
B26: Marc l'heureux | C26: 174.82 | D26: Virement | E26: 999273 | G26: 506.82 | H26: 582.72
B27: Stephanie Pellerin | C27: 76.79 | D27: Credit | E27: 907413 | G27: 222.63 | H27: 255.97
B28: Philippe Duchesne | C28: 140.01 | D28: Virement | E28: 945863 | G28: 405.9 | H28: 466.68 | K28: veut lavage int/ext durant le printemps et lavage ext durant l'automne
B29: Angela Ciolofan | C29: 151.53 | D29: Cheque | E29: 951199 | G29: 151.53 | H29: 174.22

Sheet VENTES FLAVIE R.
B1: Client | C1: Valeur dépot | D1: Type paiement | E1: #contrat | G1: Valeur contrat | H1: Valeur aprés taxes | I1: Upsell | K1: Date de rappel production
B2: Philippe Bellefeuille | C2: 112.68 | D2: Crédit | E2: 994014 | G2: 326.56 | H2: 375.47$ | I2: - | K2: Juin
B3: Lise Caron | C3: 114.11$ | D3: Pas de dépôt | E3: 911125 | G3: 330.82 | H3: 380.37$ | K3: appeller en mai pour faire un dépôt
B4: Catherine Dufour | C4: 161.25$ | D4: Pas de dépôt | E4: 911125 | G4: 467.5 | H4: 537.51$ | K4: appeller en mai pour faire un dépôt
B5: Isabelle Leveillée | C5: 240.93$ | D5: Crédit | E5: 911125 | G5: 698.5 | H5: 803.10$ | K5: Mi-juin
B6: Natacha Simard | C6: 136.59$ | D6: Crédit | E6: 959115 | G6: 396 | H6: 455.30$ | K6: Juin
B7: Marie Beauregard | C7: 66.78 | D7: Virement Interac | E7: 922940 | G7: 193.6 | H7: 222.59$ | K7: Mi-mai
B8: Carole Lacasse | C8: 154.80$ | D8: Pas de dépôt | E8: 936403 | G8: 448.8 | H8: 516.01$ | K8: Fin-mai
B9: Marie-Ève Drolet | C9: 47.43$ | D9: Crédit | E9: 971293 | G9: 137.50$ | H9: 158.09$ | K9: Juin
G10: 2997
B12: Denis Cordeau | C12: 72.85$ | D12: Crédit | E12: 909536 | G12: 211.20$ | H12: 242.83$ | K12: Juin
B13: Pascale Drolet | C13: Crossbooking (peinture)
B14: Catherine Foisy | C14: 42.43$ | D14: Pas de dépôt | E14: 922131 | G14: 123.00$ | H14: 141.42$ | K14: Juin
B15: Julie Paiement | C15: 87.27$ | D15: Crédit | E15: 946147 | G15: 253.00$ | H15: 290.89$ | K15: Juin

Sheet VENTE PATRICE G.
A1: date | B1: Client | C1: Valeur dépot | D1: Type paiement | E1: #contrat | G1: Valeur contrat | H1: Valeur aprés taxes | I1: Upsell | K1: Date de rappel production
A2: 43913 | B2: Lise Barrette | C2: 98.96 | D2: Crédit | E2: 925535 | G2: 302 | K2: mi juin
A3: 43913 | B3: Manon Dufour | C3: 65.9 | D3: Crédit | E3: 932457 | G3: 212.3 | K3: mi juin
A4: 43913 | B4: Rebeka Fortin | C4: 108.99 | D4: Crédit | E4: 918464 | G4: 315.98 | K4: mi juin
A5: 43913 | B5: Steve Nyle | C5: 294.82 | D5: Crédit | E5: 978693 | G5: 899.71 | K5: mi juin
A6: 43913 | B6: Yves Dechesne | C6: 69.75 | D6: Crédit | E6: 8KSB5X1TE25GJ | G6: 202.22 | K6: mi juin
A7: 43913 | B7: Maxime Potvin | C7: 192.93 | D7: Crédit | E7: 949132 | G7: 559.35 | K7: mi juin
G8: =SUM(G2:G7) -> 2491.56 | K8: mi juin
A9: date | B9: Client | C9: Valeur dépot | D9: Type paiement | E9: #contrat | G9: Valeur contrat | H9: Valeur aprés taxes | I9: Upsell | K9: Date de rappel production
A10: 43914 | B10: Antoine Lemelin | C10: 292.96 | D10: Credit | E10: 908014 | G10: 849.35 | K10: mi juin
A11: 43914 | B11: Alex Delisle | C11: 27.59 | D11: Credit | E11: 983447 | G11: 80 | K11: mi juin
A12: 43914 | B12: André Couturier | C12: - | D12: Credit | E12: 912600 | F12: 150 | K12: mi juin
A13: 43914 | B13: Dan Maltais | C13: 110.38 | D13: Credit | E13: 915792 | G13: 320 | K13: mi juin
A14: 43914 | B14: Anne-Marie Chapeleau | C14: 137.97 | D14: Credit | E14: 990202 | G14: 400 | K14: mi juin
A15: 43914 | B15: Mario Duplin | C15: 189.71 | D15: Credit | E15: 943807 | G15: 550 | K15: mi juin
A16: 43914 | B16: Huguette Moboya | C16: 55.19 | D16: Credit | E16: 972546 | G16: 160 | K16: mi juin
A17: 43914 | B17: Denise Coulombe | C17: Client depuis plusieurs anné donne pas de dépot | E17: 959430 | F17: 1035
G18: =SUM(G10:G17) -> 2359.35
A19: date | B19: Client | C19: Valeur dépot | D19: Type paiement | E19: #contrat | G19: Valeur contrat | H19: Valeur aprés taxes | I19: Upsell | K19: Date de rappel production
A20: 43915 | B20: Olga Hel-Bongo | C20: 170.74 | D20: Credit | E20: 947454 | G20: 495 | K20: mi juin
A21: 43915 | B21: Suzie Baronnet | C21: 144.87 | D21: Credit | E21: 912850 | G21: 420 | K21: mi juin
A22: 43915 | B22: Benoit robichaud | C22: Prend le service mais veut pas donner de dépot | D22: Credit | E22: 955309 | F22: 565 | K22: mi juin
A23: 43915 | B23: Sylvain Lirette | C23: Client depuis plusieurs anné donne pas de dépot | D23: Credit | E23: 997054 | F23: 347 | K23: mi juin
A24: 43915 | B24: Carl Patry | C24: 130.9 | D24: Credit | E24: 948809 | G24: 379.5 | K24: mi juin
A25: 43915 | B25: Michelle Duranc | C25: 90.72 | D25: Credit | E25: 992622 | G25: 263 | K25: mi juin
A26: 43915 | B26: Thierry Brochu | C26: 160.48 | D26: Credit | E26: 942841 | G26: 465.25 | K26: mi juin
A27: 43915 | B27: Anne Gagnon | C27: 119 | D27: Credit | E27: 900100 | G27: 345 | K27: mi juin
A28: 43915 | B28: Josette Rivard | C28: 89.85 | D28: Credit | E28: 947821 | G28: 260.5 | K28: mi juin
A29: 43915 | B29: Marc andre descote | C29: 258.35 | D29: Credit | E29: 949869 | G29: 749 | K29: mi juin
G30: =SUM(G20:G29) -> 3377.25
G31: =SUM(G30,G18,G8) -> 8228.16

Sheet VENTE JOHN TASSI
A1: date | B1: Client | C1: Valeur dépot | D1: Type paiement | E1: #contrat | G1: Valeur contrat | H1: Valeur aprés taxes | I1: Upsell | K1: Date de rappel production
A2: 43927 | B2: DELIA D | C2: 101.15 | D2: credit | G2: 293.25 | K2: mi juin
A3: 43927 | B3: Marika Viens | C3: 81.06 | D3: credit | E3: 964317 | G3: 235 | K3: mi juin
A4: 43927 | B4: Brigitte Dupriez | C4: 187.98 | D4: credit | E4: 967004 | G4: 545 | K4: mi juin
A5: 43927 | B5: Louise Laplante | C5: 210.73 | D5: credit | E5: 999221 | G5: 610.94 | K5: mi juin
G6: =SUM(G2:G5) -> 1684.19
A7: date | B7: Client | C7: Valeur dépot | D7: Type paiement | E7: #contrat | G7: Valeur contrat | H7: Valeur aprés taxes | I7: Upsell | K7: Date de rappel production
A8: 43928 | B8: Pascale Rancourt | C8: 88.30 | D8: credit | E8: 981754 | G8: 256 | K8: mi juin
A9: 43928 | B9: Provost Audrey | C9: 59.33 | D9: virement | E9: 981754 | F9: meme contrat ?? | G9: 172 | K9: mi juin
G10: =SUM(G8:G9) -> 428
A11: date | B11: Client | C11: Valeur dépot | D11: Type paiement | E11: #contrat | G11: Valeur contrat | H11: Valeur aprés taxes | I11: Upsell | K11: Date de rappel production
A12: 43929 | B12: Raymond roy | C12: 136.5 | D12: credit | E12: 916718 | G12: 395.75 | K12: mi juin
A13: 43929 | B13: Steven Chealsey | C13: 269.03 | D13: credit | E13: 953732 | G13: 779.96 | K13: mi mai
A14: 43929 | B14: Louise Girouard | C14: veut payer apres l'entretien | D14: pas de dépot | E14: 916524 | G14: 769 | K14: mi juin
A15: 43929 | B15: Pierre Blache | C15: 116.41 | D15: crédit | E15: 911626 | G15: 337.5 | K15: mi juin
A16: 43929 | B16: Marc Stephan | C16: 80.82 | D16: crédit | E16: 919582 | G16: 234.32 | K16: mi juin
G17: =SUM(G12:G16) -> 2516.53 | K17: mi juin
A18: date | B18: Client | C18: Valeur dépot | D18: Type paiement | E18: #contrat | G18: Valeur contrat | H18: Valeur aprés taxes | I18: Upsell | K18: Date de rappel production
A19: 43930 | B19: Paul de la Sablonnière | C19: 51.74 | D19: Interac | E19: 980443 | G19: 150 | K19: mi juin
A20: 43930 | B20: Sylvain Denoncourt | C20: 60.02 | D20: credit | E20: 922496 | G20: 174 | K20: mi mai urgent a contacter le 11 mai
A21: 43930 | B21: Luc Poirier | C21: veut payer apres l'entretien | D21: pas de dépot | E21: 963581 | G21: 216.67 | K21: mi juin
G22: =SUM(G19:G21) -> 540.67 | K22: mi juin
A23: date | B23: Client | C23: Valeur dépot | D23: Type paiement | E23: #contrat | G23: Valeur contrat | H23: Valeur aprés taxes | I23: Upsell | K23: Date de rappel production
A24: 43931 | B24: Alain Quiron | C24: veut payer apres l'entretien | D24: pas de dépot | E24: 986410 | G24: 218 | K24: mi juin
A25: 43931 | B25: Jessica Brassard | C25: 51.61 | D25: INTERAC | E25: 941042 | G25: 149.63 | K25: mi juin | L25: 2018
G26: =SUM(G24:G25) -> 367.63 | K26: mi juin
A27: date | B27: Client | C27: Valeur dépot | D27: Type paiement | E27: #contrat | G27: Valeur contrat | H27: Valeur aprés taxes | I27: Upsell | K27: Date de rappel production
A28: 43932 | B28: Jeannine Lacasse | C28: 143.58 | D28: crédit | E28: 974993 | G28: 416.25 | K28: mi mai
A29: 43932 | B29: Mathieu Labbe | C29: 103.48 | D29: crédit | E29: 986880 | G29: 300 | K29: juin
A30: 43932 | B30: Helene Lacerte | C30: veut payer apres l'entretien | D30: pas de dépot | E30: 961139 | G30: 120 | K30: mi juin
G31: =SUM(G28:G30) -> 836.25
A32: TOTAL SEMAINE | B32: =SUM(G31,G26,G22,G17,G10,G6) -> 6373.27
A33: date | B33: Client | C33: Valeur dépot | D33: Type paiement | E33: #contrat | G33: Valeur contrat | H33: Valeur aprés taxes | I33: Upsell | K33: Date de rappel production
A34: 43934 | B34: Jean-Francois Transon | C34: 132.8 | D34: crédit | E34: 960269 | G34: 385 | K34: mi juin
A35: 43934 | B35: Ginette Léonard | C35: veut payer apres l'entretien | D35: pas de dépot | E35: 916489 | G35: 240 | K35: mi juin
G36: =SUM(G34:G35) -> 625
A37: date | B37: Client | C37: Valeur dépot | D37: Type paiement | E37: #contrat | G37: Valeur contrat | H37: Valeur aprés taxes | I37: Upsell | K37: Date de rappel production
A38: 43935 | B38: Annie Carrier | C38: veut payer apres l'entretien | D38: pas de dépot | E38: 997317 | G38: 260 | K38: mi juin
A39: 43935 | B39: Diane Chatigny | C39: 206.18 | D39: chèque | E39: 967797 | G39: 597.75 | K39: mi juin
G40: =SUM(G38:G39) -> 857.75
A41: date | B41: Client | C41: Valeur dépot | D41: Type paiement | E41: #contrat | G41: Valeur contrat | H41: Valeur aprés taxes | I41: Upsell | K41: Date de rappel production
A42: 43936 | B42: Alain Pelletier | C42: 100.03 | D42: crédit | E42: 975353 | G42: 290 | K42: mai
G43: =SUM(G42) -> 290
A44: date | B44: Client | C44: Valeur dépot | D44: Type paiement | E44: #contrat | G44: Valeur contrat | H44: Valeur aprés taxes | I44: Upsell | K44: Date de rappel production
A45: 43937 | B45: Suzanne Chayer | C45: 118.65 | D45: crédit | E45: 979799 | G45: 344 | K45: mi juin
A46: 43937 | B46: Elodie Lemieux | C46: 171.43 | D46: en attente | E46: 906670 | G46: 497 | K46: mi juin
A47: 43937 | B47: Marie Simone Icart | C47: 34.49 | D47: crédit | E47: 926173 | G47: 100 | K47: mi juin
G48: =SUM(G45:G46) -> 841
A49: date | B49: Client | C49: Valeur dépot | D49: Type paiement | E49: #contrat | G49: Valeur contrat | H49: Valeur aprés taxes | I49: Upsell | K49: Date de rappel production
A50: 43938 | B50: Mireille Dupuis | C50: 71.28 | D50: interac | E50: 904685 | G50: 206.66 | K50: mi juin
A51: 43938 | B51: Gui Geannot | C51: 118.65 | D51: interrac | E51: 940327 | G51: 344 | K51: début mai
A52: 43938 | B52: Margo Heron | C52: 91.41 | D52: credit | E52: 936269 | G52: 265 | K52: mi juin
A53: 43938 | B53: Jim Fodi | C53: 142.77 | D53: chèque | E53: 977013 | G53: 413.91 | K53: mai
A54: 43938 | B54: Monique Jones | C54: 53.46 | E54: 932937 | G54: 155 | K54: production le 2020-06-02
G55: =SUM(G50:G54) -> 1384.57
A56: TOTAL SEMAINE | B56: =SUM(G55,G48,G43,G40,G36) -> 3998.32
A57: date | B57: Client | C57: Valeur dépot | D57: Type paiement | E57: #contrat | G57: Valeur contrat | H57: Valeur aprés taxes | I57: Upsell | K57: Date de rappel production
A58: 43941 | B58: AHMED CHAABAN | C58: 181.09 | D58: en attente | E58: 903346 | G58: 525 | K58: mi juin
K59: mi juin
K60: mi juin
K61: mi juin
K62: mi juin
G63: =SUM(G58:G62) -> 525

Sheet VENTE FANIA

Sheet VENTE JOÉ
A1: DATE | B1: Client | C1: Valeur dépot | D1: Type paiement | E1: #contrat | G1: Valeur contrat | H1: Valeur aprés taxes | I1: Upsell | K1: Date de rappel production
A2: 43917 | B2: Jacques Gauvin | C2: =0.3*H2 -> 137.169 | D2: credit | E2: 65955 | F2: 2019 | G2: 388.76 | H2: 457.23 | K2: mi-juin
A3: 43914 | B3: georges clerinx | C3: =0.3*H3 -> 92.229 | D3: credit | E3: 931302 | F3: 2019 | G3: 261.32 | H3: 307.43 | K3: mi-juin
A4: 43914 | B4: Oscar | C4: =0.3*H4 -> 149.127 | D4: credit | E4: 975513 | F4: 2019 | G4: 422.53 | H4: 497.09 | K4: mi-juin
A5: 43910 | B5: carmen garcia | C5: =0.3*H5 -> 139.7007 | D5: credit | E5: 969805 | F5: 2019 | G5: 405 | H5: =G5*1.1498 -> 465.669 | K5: mi-juin
A6: 43913 | B6: nikki | C6: =0.3*H6 -> 195.40851 | D6: credit | E6: 967718 | F6: 2019 | G6: 566.5 | H6: =G6*1.1498 -> 651.3617 | K6: mi-juin
A7: 43920 | B7: marie claude | C7: =0.3*H7 -> 137.976 | D7: cheque | F7: 2019 | G7: 400 | H7: =G7*1.1498 -> 459.92 | K7: mi-juin
A8: 43911 | B8: marie -therese clermont | C8: =0.3*H8 -> 155.06433 | D8: virement | F8: 2019 | G8: 449.54 | H8: =G8*1.1498 -> 516.88109 | K8: mi-juin
A9: DATE | B9: Client | C9: Valeur dépot | D9: Type paiement | E9: #contrat | G9: Valeur contrat | H9: Valeur aprés taxes | I9: Upsell | K9: Date de rappel production
A10: 43923 | B10: andré giroux | C10: =0.3*H10 -> 0 | D10: credit | F10: 2017 | H10: =G10*1.1498 -> 0 | K10: mi-juin
A11: 43923 | B11: robert grelot | C11: =0.3*H11 -> 0 | D11: credit | E11: 942716 | F11: 2019 | H11: =G11*1.1498 -> 0 | K11: mi-juin
A12: 43923 | B12: rachel gagnon | C12: =0.3*H12 -> 0 | D12: credit | E12: 991945 | F12: 2019 | H12: =G12*1.1498 -> 0 | K12: mi-juin
A13: 43923 | B13: ncolabi | C13: =0.3*H13 -> 0 | D13: virement | E13: 965019 | F13: 2019 | H13: =G13*1.1498 -> 0 | K13: mi-juin
C14: =0.3*H14 -> 0 | E14: 936890 | F14: 2018 | H14: =G14*1.1498 -> 0 | K14: mi-juin
A15: 43923 | B15: paul gemme | C15: =0.3*H15 -> 0 | E15: 939065 | F15: 2017 | H15: =G15*1.1498 -> 0 | K15: mi-juin
C16: =0.3*H16 -> 0 | D16: virement | E16: 931175 | F16: 2019 | H16: =G16*1.1498 -> 0 | K16: mi-juin
C17: =0.3*H17 -> 0 | D17: credit | E17: 918356 | F17: 2019 | H17: =G17*1.1498 -> 0 | K17: mi-juin
A18: DATE | B18: Client | C18: Valeur dépot | D18: Type paiement | E18: #contrat | G18: Valeur contrat | H18: Valeur aprés taxes | I18: Upsell | K18: Date de rappel production
C19: =0.3*H19 -> 0 | D19: credir | E19: 984324 | F19: 2017 | H19: =G19*1.1498 -> 0 | K19: mi-juin
A20: 43924 | B20: sylvie lauzon | C20: =0.3*H20 -> 0 | D20: credit | E20: 910942 | F20: 2017 | H20: =G20*1.1498 -> 0 | K20: mi-juin
B21: brousseau | C21: =0.3*H21 -> 0 | D21: credi | E21: 904169 | F21: 2017 | H21: =G21*1.1498 -> 0 | K21: mi-juin
B22: Joe Balazic | C22: =0.3*H22 -> 0 | D22: virment | E22: 175 | F22: envoyer contrat | H22: =G22*1.1498 -> 0 | K22: mi-juin
B23: syvlie cote | C23: =0.3*H23 -> 0 | D23: cheque (clinique) | F23: 2017 | H23: =G23*1.1498 -> 0 | K23: mi-juin
B24: carline coulombe | C24: =0.3*H24 -> 0 | D24: credit | E24: 958880 | F24: 2018 | H24: =G24*1.1498 -> 0 | K24: mi-juin
B25: lucien caron | C25: =0.3*H25 -> 0 | D25: cheque (navais pas les numeros a larriere???) | F25: envoyer contrat | H25: =G25*1.1498 -> 0 | K25: mi-juin
B26: maryline | C26: =0.3*H26 -> 0 | D26: credit | E26: 941317 | F26: 2019 | H26: =G26*1.1498 -> 0 | K26: mi-juin
B27: ** | C27: =0.3*H27 -> 0 | D27: credit | E27: checker clover | F27: 2019 | H27: =G27*1.1498 -> 0 | K27: mi-juin
B28: johanne deneault | C28: =0.3*H28 -> 0 | D28: credit | E28: 902365 | F28: 2019 | H28: =G28*1.1498 -> 0 | K28: mi-juin
B29: carole breton | C29: =0.3*H29 -> 0 | D29: credit | E29: 900474 | F29: 2019 | H29: =G29*1.1498 -> 0 | K29: mi-juin
B30: amelia roy | C30: =0.3*H30 -> 0 | D30: credit | E30: 988375 | F30: 2019 | H30: =G30*1.1498 -> 0 | K30: mi-juin
C31: =0.3*H31 -> 0 | D31: virement | E31: 977058 | F31: envoyeer | H31: =G31*1.1498 -> 0 | K31: mi-juin
B32: Carmelo Bonadonna | C32: =0.3*H32 -> 0 | D32: pas recu service lan passe | F32: 2019 | H32: =G32*1.1498 -> 0 | K32: mi-juin
B33: paquette | C33: =0.3*H33 -> 0 | E33: 957531 | F33: 2019 | H33: =G33*1.1498 -> 0 | K33: mi-juin
B34: claire bergeron | C34: =0.3*H34 -> 0 | E34: 927638 | F34: 2019 | H34: =G34*1.1498 -> 0 | K34: mi-juin
A35: DATE | B35: Client | C35: Valeur dépot | D35: Type paiement | E35: #contrat | G35: Valeur contrat | H35: Valeur aprés taxes | I35: Upsell | K35: Date de rappel production
A36: 700 vincent** | C36: =0.3*H36 -> 0 | F36: 2019 | H36: =G36*1.1498 -> 0 | K36: mi-juin
A37: 43925 | B37: nam tu le | C37: =0.3*H37 -> 120.729 | E37: 997492 | F37: 2019 | G37: 350 | H37: =G37*1.1498 -> 402.43 | K37: mi-juin
B38: me rappel pour carte | C38: =0.3*H38 -> 99.34272 | F38: 2019 | G38: 288 | H38: =G38*1.1498 -> 331.1424 | K38: mi-juin
B39: benard | C39: =0.3*H39 -> 64.50378 | E39: 975274 | F39: 2019 | G39: 187 | H39: =G39*1.1498 -> 215.0126 | K39: mi-juin
B40: sylvie dallaire | C40: =0.3*H40 -> 75.8868 | E40: 990141 | F40: 2019 | G40: 220 | H40: =G40*1.1498 -> 252.956 | K40: mi-juin
B41: faluk | C41: =0.3*H41 -> 28.28508 | F41: 2019 | G41: 82 | H41: =G41*1.1498 -> 94.2836 | K41: mi-juin
C42: =0.3*H42 -> 48.2916 | E42: 985684 | G42: 140 | H42: =G42*1.1498 -> 160.972 | K42: mi-juin
C43: =0.3*H43 -> 117.2796 | G43: 340 | H43: =G43*1.1498 -> 390.932 | K43: mi-juin
B44: deslauriers | C44: =0.3*H44 -> 47.60172 | E44: 954002 | G44: 138 | H44: =G44*1.1498 -> 158.6724 | K44: mi-juin
C45: =0.3*H45 -> 85.54512 | E45: 987458 | G45: 248 | H45: =G45*1.1498 -> 285.1504 | K45: mi-juin
B46: vezina | C46: =0.3*H46 -> 151.7736 | D46: credit | E46: 973586 | G46: 440 | H46: =G46*1.1498 -> 505.912 | K46: mi-juin
A47: DATE | B47: Client | C47: Valeur dépot | D47: Type paiement | E47: #contrat | G47: Valeur contrat | H47: Valeur aprés taxes | I47: Upsell | K47: Date de rappel production
A48: 43927 | C48: =0.3*H48 -> 60.3645 | E48: 919702 | G48: 175 | H48: =G48*1.1498 -> 201.215 | K48: mi-juin
C49: =0.3*H49 -> 137.976 | E49: 946396 | G49: 400 | H49: =G49*1.1498 -> 459.92 | K49: mi-juin
C50: =0.3*H50 -> 51.741 | E50: 993451 | G50: 150 | H50: =G50*1.1498 -> 172.47 | K50: mi-juin
B51: samuel parent | C51: =0.3*H51 -> 94.8585 | E51: 956604 | G51: 275 | H51: =G51*1.1498 -> 316.195 | I51: carte fonctionne pas**** | K51: mi-juin
B52: brigitte | C52: =0.3*H52 -> 37.9434 | E52: 921765 | G52: 110 | H52: =G52*1.1498 -> 126.478 | K52: mi-juin
B53: jf francois | C53: =0.3*H53 -> 225.24582 | D53: virement | G53: 653 | H53: =G53*1.1498 -> 750.8194 | K53: mi-juin
B54: rose et claude | C54: =0.3*H54 -> 212.82798 | E54: 938368 | G54: 617 | H54: =G54*1.1498 -> 709.4266 | K54: mi-juin
B55: poulin | C55: =0.3*H55 -> 97.27308 | E55: 966960 | G55: 282 | H55: =G55*1.1498 -> 324.2436 | K55: mi-juin
B56: fred desroches | C56: =0.3*H56 -> 98.99778 | D56: pas recu services | G56: 287 | H56: =G56*1.1498 -> 329.9926 | K56: mi-juin
B57: rolland gagon | C57: =0.3*H57 -> 125.21322 | E57: 930550 | G57: 363 | H57: =G57*1.1498 -> 417.3774 | K57: mi-juin
C58: =0.3*H58 -> 76.57668 | E58: 997309 | G58: 222 | H58: =G58*1.1498 -> 255.2556 | K58: mi-juin
C59: =0.3*H59 -> 75.8868 | E59: 954298 | G59: 220 | H59: =G59*1.1498 -> 252.956 | K59: mi-juin
B60: poirier | C60: =0.3*H60 -> 232.8345 | E60: 912963 | G60: 675 | H60: =G60*1.1498 -> 776.115 | K60: mi-juin
C61: =0.3*H61 -> 194.8911 | E61: 934746 | G61: 565 | H61: =G61*1.1498 -> 649.637 | K61: mi-juin
C62: =0.3*H62 -> 41.3928 | E62: 907442 | G62: 120 | H62: =G62*1.1498 -> 137.976 | K62: mi-juin
A63: DATE | B63: Client | C63: Valeur dépot | D63: Type paiement | E63: #contrat | G63: Valeur contrat | H63: Valeur aprés taxes | I63: Upsell | K63: Date de rappel production
B64: gaetan lantagne | C64: =0.3*H64 -> 100.0326 | E64: 982665 | G64: 290 | H64: =G64*1.1498 -> 333.442 | K64: mi-juin
A65: 43928 | C65: =0.3*H65 -> 129.3525 | E65: 949634 | G65: 375 | H65: =G65*1.1498 -> 431.175 | K65: mi-juin
B66: desmarais | C66: =0.3*H66 -> 120.729 | E66: 984217 | G66: 350 | H66: =G66*1.1498 -> 402.43 | K66: mi-juin
B67: stephanie | C67: =0.3*H67 -> 40.01304 | E67: 928564 | G67: 116 | H67: =G67*1.1498 -> 133.3768 | K67: mi-juin
B68: oranger | C68: =0.3*H68 -> 150.73878 | E68: 956912 | G68: 437 | H68: =G68*1.1498 -> 502.4626 | K68: mi-juin
B69: belanger | C69: =0.3*H69 -> 93.47874 | E69: 989754 | G69: 271 | H69: =G69*1.1498 -> 311.5958 | K69: mi-juin
B70: steve brien | C70: =0.3*H70 -> 103.482 | G70: 300 | H70: =G70*1.1498 -> 344.94 | K70: mi-juin
B71: rondeau | C71: =0.3*H71 -> 68.988 | E71: 922832 | G71: 200 | H71: =G71*1.1498 -> 229.96 | K71: mi-juin
B72: iara | C72: =0.3*H72 -> 110.3808 | E72: 911133 | G72: 320 | H72: =G72*1.1498 -> 367.936 | K72: mi-juin
B73: irene | C73: =0.3*H73 -> 117.2796 | E73: 998707 | G73: 340 | H73: =G73*1.1498 -> 390.932 | K73: mi-juin
A74: DATE | B74: Client | C74: Valeur dépot | D74: Type paiement | E74: #contrat | G74: Valeur contrat | H74: Valeur aprés taxes | I74: Upsell | K74: Date de rappel production | M74: DATE | N74: Client | O74: Valeur dépot | P74: Type paiement | Q74: #contrat | S74: Valeur contrat | T74: Valeur aprés taxes | U74: Upsell | W74: Date de rappel production
A75: 43929 | B75: louise | C75: =0.3*H75 -> 85.89006 | E75: 955796 | G75: 249 | H75: =G75*1.1498 -> 286.3002 | K75: mi-juin
B76: morency | C76: =0.3*H76 -> 143.83998 | E76: 905784 | G76: 417 | H76: =G76*1.1498 -> 479.4666 | K76: mi-juin
B77: annie | C77: =0.3*H77 -> 96.5832 | E77: 954942 | G77: 280 | H77: =G77*1.1498 -> 321.944 | K77: mi-juin
B78: desroches | C78: =0.3*H78 -> 99.68766 | E78: 982841 | G78: 289 | H78: =G78*1.1498 -> 332.2922 | K78: mi-juin
B79: remillard | C79: =0.3*H79 -> 110.3808 | E79: 955739 | G79: 320 | H79: =G79*1.1498 -> 367.936 | K79: mi-juin
B80: le porcs | C80: =0.3*H80 -> 131.0772 | D80: virement | E80: 981029 | G80: 380 | H80: =G80*1.1498 -> 436.924 | K80: mi-juin
B81: vanessa | C81: =0.3*H81 -> 110.3808 | E81: 942556 | G81: 320 | H81: =G81*1.1498 -> 367.936 | K81: mi-juin
B82: maryse | C82: =0.3*H82 -> 136.94118 | E82: 926667 | G82: 397 | H82: =G82*1.1498 -> 456.4706 | K82: mi-juin
B83: richer | C83: =0.3*H83 -> 136.2513 | E83: 995904 | G83: 395 | H83: =G83*1.1498 -> 454.171 | K83: mi-juin
C84: =0.3*H84 -> 48.2916 | E84: 949903 | G84: 140 | H84: =G84*1.1498 -> 160.972 | K84: mi-juin
B85: carrier | C85: =0.3*H85 -> 51.741 | D85: cheque tbk | E85: 902204 | G85: 150 | H85: =G85*1.1498 -> 172.47 | K85: mi-juin
B86: pilote | C86: =0.3*H86 -> 55.1904 | E86: 934077 | G86: 160 | H86: =G86*1.1498 -> 183.968 | K86: mi-juin
B87: nadia | C87: =0.3*H87 -> 94.8585 | E87: 963579 | G87: 275 | H87: =G87*1.1498 -> 316.195 | K87: mi-juin
B88: page | C88: =0.3*H88 -> 96.5832 | E88: (418) 550-5064 | G88: 280 | H88: =G88*1.1498 -> 321.944 | K88: mi-juin
B89: normand | C89: =0.3*H89 -> 155.223 | E89: 985924 | G89: 450 | H89: =G89*1.1498 -> 517.41 | K89: mi-juin
A90: DATE | B90: Client | C90: Valeur dépot | D90: Type paiement | E90: #contrat | G90: Valeur contrat | H90: Valeur aprés taxes | I90: Upsell | K90: Date de rappel production | M90: DATE | N90: Client | O90: Valeur dépot | P90: Type paiement | Q90: #contrat | S90: Valeur contrat | T90: Valeur aprés taxes | U90: Upsell | W90: Date de rappel production
A91: 43931 | B91: helene | C91: =0.3*H91 -> 48.2916 | E91: 989144 | G91: 140 | H91: =G91*1.1498 -> 160.972 | K91: mi-juin
B92: constance vaillancourt | C92: =0.3*H92 -> 68.988 | E92: 932029 | G92: 200 | H92: =G92*1.1498 -> 229.96 | K92: mi-juin
B93: donald larose | C93: =0.3*H93 -> 95.54838 | G93: 277 | H93: =G93*1.1498 -> 318.4946 | K93: mi-juin
C94: =0.3*H94 -> 0 | H94: =G94*1.1498 -> 0 | K94: mi-juin
B95: caroline richard | C95: =0.3*H95 -> 67.2633 | E95: 980869 | G95: 195 | H95: =G95*1.1498 -> 224.211 | K95: mi-juin
B96: martin biellard | C96: =0.3*H96 -> 99.34272 | D96: virement | E96: 995516 | G96: 288 | H96: =G96*1.1498 -> 331.1424 | K96: mi-juin
B97: jean poulin | C97: =0.3*H97 -> 63.8139 | D97: complet | E97: 948122 | G97: 185 | H97: =G97*1.1498 -> 212.713 | K97: mi-juin
B98: sebastien paquette | C98: =0.3*H98 -> 101.7573 | D98: virement recu | E98: 926168 | G98: 295 | H98: =G98*1.1498 -> 339.191 | K98: mi-juin
A99: DATE | B99: Client | C99: Valeur dépot | D99: Type paiement | E99: #contrat | G99: Valeur contrat | H99: Valeur aprés taxes | I99: Upsell | K99: Date de rappel production
C100: =0.3*H100 -> 0
...

Sheet VENTE REMI
A1: DATE | B1: Client | C1: Valeur dépot | D1: Type paiement | E1: #contrat | G1: Valeur contrat | H1: Valeur aprés taxes | I1: Upsell | K1: Date de rappel production

Sheet VENTE COLLIN
A1: DATE | B1: Client | C1: Valeur dépot | D1: Type paiement | E1: #contrat | G1: Valeur contrat | H1: Valeur aprés taxes | I1: Upsell | K1: Date de rappel production

Sheet VENTE WADIH
A1: DATE | B1: Client | C1: Valeur dépot | D1: Type paiement | E1: #contrat | G1: Valeur contrat | H1: Valeur aprés taxes | I1: Upsell | K1: Date de rappel production
K2: mi-juin
K3: mi-juin
K4: mi-juin
K5: mi-juin
K6: mi-juin
K7: mi-juin
K8: mi-juin
K9: mi-juin
K10: mi-juin
K11: mi-juin
K12: mi-juin
K13: mi-juin
... K16: mi-juin

Sheet VENTE XAVIER
A1: DATE | B1: Client | C1: Valeur dépot | D1: Type paiement | E1: #contrat | G1: Valeur contrat | H1: Valeur aprés taxes | I1: Upsell | K1: Date de rappel production
A2: 43571 | B2: Annie DeChamplain | C2: =H2*0.3 -> 15.521625 | D2: virement | E2: 996941 | G2: 45 | H2: =G2*1.14975 -> 51.73875 | K2: début juin
A3: 43937 | B3: Mario Rivard | C3: =H3*0.3 -> 74.5038 | D3: crédit | E3: 996941 | G3: 216 | H3: =G3*1.14975 -> 248.346 | K3: début juin
A4: 43937 | B4: Michael Pelletier | C4: =H4*0.3 -> 71.551242 | D4: crédit | E4: 996941 | G4: 207.44 | H4: =G4*1.14975 -> 238.50414 | K4: mi juin
A5: 43571 | C5: =H5*0.3 -> 0 | H5: =G5*1.14975 -> 0
A6: 43937 | C6: =H6*0.3 -> 0 | H6: =G6*1.14975 -> 0
A7: 43937 | C7: =H7*0.3 -> 0 | H7: =G7*1.14975 -> 0
A8: 43571 | C8: =H8*0.3 -> 0 | H8: =G8*1.14975 -> 0
A9: 43937 | C9: =H9*0.3 -> 0 | H9: =G9*1.14975 -> 0
A10: 43937 | C10: =H10*0.3 -> 0
A11: 43571 | C11: =H11*0.3 -> 0
A12: 43937 | C12: =H12*0.3 -> 0
A13: 43937 | C13: =H13*0.3 -> 0

Sheet VENTE ANNEMARIE

Sheet Ventes Partis
A1: Téléphoniste | B1: Date | C1: Client | D1: Valeur dépot | E1: Type paiement | F1: #contrat | H1: Valeur contrat | I1: Valeur après taxes | J1: Upsell | L1: Date de rappel production
A2: Benjamin | B2: 43909 | C2: rachelle boissonnault. 39 | E2: crédit | F2: 931043 | H2: 114.25 | I2: 130.05
A3: Benjamin | B3: 43909 | C3: marlene danies | D3: 45 | E3: cheque | F3: 954727 | H3: 132
A4: Yvan | C4: Lucie Dionne | D4: 90.11 | E4: crédit | F4: 923050 | H4: 261.25 | I4: 300.37 | L4: 44002
A5: Yvan | C5: Suzanne Métras | D5: 94.85 | E5: crédit | F5: 980297 | H5: 275 | I5: 316.18 | L5: 44002
A6: Zeina | C6: Jean-Louis Miglietti | D6: 116.1 | E6: carte de credit | F6: 947843 | H6: 336.6 | I6: 387.01
A7: Zeina | C7: Johanne Goupil | D7: a ete paye en 2019 | E7: interac | F7: 910290 | H7: 115.6 | I7: 132.91
A8: Zeina | C8: Celine Soulieres | D8: 93.45 | E8: carte de credit | F8: 949933 | H8: 270.92 | I8: 311.49
A9: Zeina | C9: Luigi Bennardi | D9: 72.43 | E9: interac | F9: 960568 | H9: 210 | I9: 241.45
A10: Zeina | C10: Miriam Celicourt | D10: a ete paye en 2019 | E10: carte de credit | F10: 961404 | H10: 209 | I10: 240.30

Sheet VENTE OLIVIER
A1: Date | B1: Date | C1: Client | D1: Valeur dépot | E1: Type paiement | F1: #contrat | H1: Valeur contrat | I1: Valeur après taxes | J1: Upsell | L1: Date de rappel production
B2: 43915 | C2: brigitte legault | D2: 83.47 | E2: credit | F2: 972445 | H2: 242 | L2: debut juin
B3: 43915 | C3: carolyne nadeau | D3: 71.14 | E3: credit | F3: 972445 | H3: 206 | L3: debut juin
B4: 43915 | C4: chantal scroggins | D4: 53.46 | E4: credit | F4: 904433 | H4: 155 | L4: debut juin
B5: 43915 | C5: francis de gruchy | D5: 67.26 | E5: credit | F5: 990088 | H5: 195 | L5: debut juin
B6: 43916 | C6: caroline maltais | D6: 217.26 | E6: virement | F6: 920176 | H6: 725 | L6: debut juin
B7: 43916 | C7: dany cloutier | D7: 84.33 | E7: credit | F7: 981085 | H7: 281 | L7: debut juin
B8: 43916 | C8: chantal gagner | D8: 37.31 | E8: cheque | F8: 933881 | H8: 124 | L8: debut juinm
B9: 43916 | C9: denise puxley | D9: 44.84 | E9: credit | F9: 914629 | H9: 130 | L9: debut juin
B10: 43916 | C10: francine guay | D10: 51.45 | E10: credit | F10: 966972 | H10: 150 | L10: debut juin
B11: 43916 | C11: julie boucher | D11: 86.89 | E11: credit | F11: 933671 | H11: 282 | L11: debut juin
B12: 43916 | C12: kate gagnon | D12: 56.91 | E12: virement | F12: 963483 | H12: 165 | L12: debut juin
B13: 43916 | C13: elaine parent | D13: 96.58 | E13: credit | F13: 975117 | H13: 280 | L13: debut juin
... B16: 43917 | C16: vanessa boucher | D16: 68.98 | E16: credit | F16: 938386 | H16: 200 | L16: debut juin
B17: 43917 | C17: philippe prive | D17: 49.49 | E17: virement | H17: 143.5 | L17: debut juin
B18: 43920 | C18: linda sans cartier | E18: pas de depot | F18: 930028 | H18: 200 | L18: debut juin
B19: 43920 | C19: michel rondeau | E19: depot payer an passer | F19: 956873 | H19: 196.66 | L19: debut juin
B20: 43920 | C20: odette perras | D20: 85 | E20: an passer | F20: 932038 | H20: 250 | L20: debut juin
B21: 43920 | C21: caroline wissa | E21: an passer | F21: 939179 | H21: 140.5 | L21: debut juin
B22: 43920 | C22: annie brochu | D22: 122.21 | E22: credit | F22: 952822 | H22: 354 | L22: debut juin
B23: 43921 | C23: sandra velasquez | D23: 65.19 | E23: virement | F23: 967243 | H23: 189 | L23: debut juin
B24: 43921 | C24: dominique viguie | D24: 120.72 | E24: credit | F24: 906341 | H24: 350 | L24: debut juin
B25: 43921 | C25: alain guernon | D25: 106.33 | E25: virement | F25: 997303 | H25: 350 | L25: debut juin
B26: 43921 | C26: alain guernon | D26: 39.32 | E26: virement | F26: 921559 | H26: 129 | L26: debut juin
B27: 43923 | C27: caroline jodoin | D27: 91 | E27: credit | F27: 914690 | H27: 264

Sheet VENTE JACYNHTE
A1: Date | B1: Client | C1: Valeur dépot | D1: Type paiement | E1: #contrat | G1: Valeur contrat | H1: Valeur après taxes | I1: Upsell | K1: Date de rappel production
A2: 43916 | B2: Gilles St-Onges | C2: 61.25 | D2: crédit | E2: 937249** | G2: 177.5 | K2: mi-juin
A3: 43916 | B3: Nicolas Dubuc | C3: 122.65 | D3: crédit | E3: 937249** | G3: 355.58 | K3: mi-juin
A4: 43916 | B4: Myriam Cayer | C4: 63.07 | D4: crédit | E4: 922008 | G4: 182.86 | K4: mi-juin
A5: 43916 | B5: Martin Casto. | C5: 91.92 | D5: crédit | E5: 940984 | G5: 266.48 | K5: mi-juin
A6: 43916 | B6: Josée Denis | C6: 104.34 | D6: crédit | E6: 976130 | G6: 302.5 | K6: mi-juin
A8: 43919 | B8: Genevieve Des. | C8: 115.72 | D8: Crédit | E8: 967993 | G8: 335.50 | K8: mi-juin
A9: 43919 | B9: Line-Marie For. | C9: 50 | D9: Crédit | E9: 915693 | G9: 143.00 | K9: mi-juin
A10: 43919 | B10: Isabelle Robert | C10: 83.47 | D10: Crédit | E10: 911406 | G10: 242.00 | K10: mi-juin
A11: 43919 | B11: Brigitte Daversin | C11: 81.57 | D11: Crédit | E11: 957960 | G11: 236.50 | K11: mi-juin/début juillet
A12: 43919 | B12: Brigitte Thomas | C12: 103.13 | D12: Crédit | E12: 903116 | G12: 313.50 | K12: Fin mai pour nett mi-juin max
A14: 43920 | B14: Genevieve Geof. | C14: 89.92 | D14: Crédit | E14: 974987 | G14: 260.7 | K14: mi-juin
A15: 43920 | B15: Claude Hamel | C15: 155.47 | D15: Crédit | E15: 905289 | G15: 450.73 | K15: mi-juin
A16: 43920 | B16: Carlo Stepancic | C16: 56.91 | D16: Crédit | E16: 977416 | G16: 165 | K16: début juin
A17: 43920 | B17: Yannick Gagnon | C17: 68.30 | D17: Crédit | E17: 996621 | G17: 198 | K17: mi-juin
A19: 43921 | B19: Raymonde Mart. | C19: 94.10 | D19: Crédit | E19: 976987 | G19: 272.8 | K19: Fin mai pour nett mi-juinm max (faire en meme temps que brigitte thomas)
A20: 43921 | B20: Marthe Bourgeois. | C20: 142.28 | D20: Crédit | E20: 964629 | G20: 412.5 | K20: mi-mai fin-mai doit être fait max mi-juin
A22: 43922 | B22: Dominic Bernier | C22: 93.13 | D22: Crédit | E22: 940908 | G22: 270 | K22: faire fin-mai max
A23: 43922 | B23: Ghislaine Fourn. | C23: 63.55 | D23: Crédit | E23: 963675 | G23: 184.25 | K23: mi-juin
A24: 43922 | B24: Claude Drolet | C24: 45.53 | D24: Crédit | E24: 925065 | G24: 132 | K24: mi-juin
A25: 43922 | B25: Genevieve Simo. | C25: 74.18 | D25: Crédit | E25: 927349 | G25: 215.06 | K25: plus rapidement possible, max mi-juin
A26: 43922 | B26: Edith Aubry | C26: 230.78 | D26: Crédit | E26: 935119 | G26: 669.08 | K26: début juin

Sheet VENTE ISMAEL
A1: Date | B1: Client | C1: Valeur dépot | D1: Type paiement | E1: #contrat | G1: Valeur contrat | H1: Valeur après taxes | I1: Upsell | K1: Date de rappel production
A2: 43917 | B2: nathalie bouchard | C2: =SUM(H2*0.3) -> 68.985 | D2: master | E2: 921182 | G2: 200 | H2: =SUM(G2*1.14975) -> 229.95 | K2: mi-juin | N2: comm 27 | O2: =SUM(G2:G20)*0.07 -> 317.66
A3: 43917 | B3: sebastien dutil | C3: =SUM(H3*0.3) -> 43.115625 | D3: master | E3: 981045 | G3: 125 | H3: =SUM(G3*1.14975) -> 143.71875 | K3: mi-juin | N3: total | O3: =SUM(G2:G30) -> 8804
A4: 43917 | B4: marie eve beaulieu | C4: =SUM(H4*0.3) -> 86.23125 | D4: credit | E4: 994419 | G4: 250 | H4: =SUM(G4*1.14975) -> 287.4375 | K4: mi-juin | N4: comm 30 | O4: =SUM(G21:G35)*0.07 -> 298.62
A5: 43917 | B5: gracias pelletier | C5: =SUM(H5*0.3) -> 97.613775 | D5: credit | E5: 925340 | G5: 283 | H5: =SUM(G5*1.14975) -> 325.37925 | K5: mi-juin | N5: total 30 | O5: =SUM(G21:G37) -> 4266
A6: 43917 | B6: lisane lavoie | C6: =SUM(H6*0.3) -> 99.3384 | D6: credit | E6: 908464 | G6: 288 | H6: =SUM(G6*1.14975) -> 331.128 | K6: mi-juin | N6: comm total | O6: =SUM(O2,O4) -> 616.28
A7: 43917 | B7: Julie Laplante | C7: =SUM(H7*0.3) -> 108.65138 | D7: credit | E7: 956069 | G7: 315 | H7: =SUM(G7*1.14975) -> 362.17125 | K7: mi-juin
A8: 43917 | B8: linda paquet | C8: =SUM(H8*0.3) -> 91.405125 | D8: credit | E8: 998938 | G8: 265 | H8: =SUM(G8*1.14975) -> 304.68375 | K8: mi-juin
A9: 43917 | B9: ginette raté | C9: =SUM(H9*0.3) -> 114.86002 | D9: credit | E9: 931364 | G9: 333 | H9: =SUM(G9*1.14975) -> 382.86675 | K9: mi-juin
A10: 43917 | B10: gilles hamel | C10: =SUM(H10*0.3) -> 103.4775 | D10: credit | E10: 991775 | G10: 300 | H10: =SUM(G10*1.14975) -> 344.925 | K10: mi-juin
A11: 43917 | B11: leopaul job | C11: =SUM(H11*0.3) -> 106.92675 | D11: cheque | E11: 979540 | G11: 310 | H11: =SUM(G11*1.14975) -> 356.4225 | K11: mi-juin
A12: 43917 | B12: josianne daigle | C12: =SUM(H12*0.3) -> 92.784825 | D12: virement | E12: 984834 | G12: 269 | H12: =SUM(G12*1.14975) -> 309.28275 | K12: mi-juin
A13: 43917 | B13: nathalie siberil | C13: =SUM(H13*0.3) -> 72.43425 | D13: credit | E13: 919466 | G13: 210 | H13: =SUM(G13*1.14975) -> 241.4475 | K13: mi-juin
A14: 43917 | B14: fernande Guimond | C14: =SUM(H14*0.3) -> 68.985 | D14: credit | E14: 904570 | G14: 200 | H14: =SUM(G14*1.14975) -> 229.95 | K14: mi-juin
A15: 43917 | B15: gerard guimont | C15: =SUM(H15*0.3) -> 76.57335 | D15: credit | E15: 917206 | G15: 222 | H15: =SUM(G15*1.14975) -> 255.2445 | K15: mi-juin
A16: 43917 | B16: martin gamache | C16: =SUM(H16*0.3) -> 71.7444 | D16: depot | E16: 999315 | G16: 208 | H16: =SUM(G16*1.14975) -> 239.148 | K16: mi-juin
A17: 43917 | B17: gilles bedard | C17: =SUM(H17*0.3) -> 68.29515 | D17: credit | E17: 903726 | G17: 198 | H17: =SUM(G17*1.14975) -> 227.6505
A18: 43917 | B18: claire Trudel | C18: =SUM(H18*0.3) -> 107.6166 | D18: credit | E18: 988049 | G18: 312 | H18: =SUM(G18*1.14975) -> 358.722 | K18: mi-juin
A19: 43917 | B19: Marie-ann Lagueux | C19: =SUM(H19*0.3) -> 86.23125 | D19: credit | E19: 984524 | G19: 250 | H19: =SUM(G19*1.14975) -> 287.4375 | K19: mi-juin
C20: =SUM(H20*0.3) -> 0 | H20: 0
A21: 43920 | B21: Isabelle Desmarais | C21: =SUM(H21*0.3) -> 171.77265 | D21: credit | E21: 943439 | G21: 498 | H21: =SUM(G21*1.14975) -> 572.5755 | K21: mi-juin
A22: 43920 | B22: francine champagna | C22: =SUM(H22*0.3) -> 120.72375 | D22: depot | E22: 962720 | G22: 350 | H22: =SUM(G22*1.14975) -> 402.4125 | K22: mi-juin
A23: 43920 | B23: collete morvan | C23: =SUM(H23*0.3) -> 117.2745 | D23: credit | E23: 955058 | G23: 340 | H23: =SUM(G23*1.14975) -> 390.915 | K23: mi-juin
A24: 43920 | B24: jacinte joyal | C24: =SUM(H24*0.3) -> 103.4775 | D24: credit | E24: 973666 | G24: 300 | H24: =SUM(G24*1.14975) -> 344.925 | K24: mi-juin
A25: 43920 | B25: francois perron | C25: =SUM(H25*0.3) -> 170.73788 | D25: credit | E25: 971889 | G25: 495 | H25: =SUM(G25*1.14975) -> 569.12625 | K25: mi-juin
A26: 43920 | B26: danny bucher | C26: =SUM(H26*0.3) -> 213.16365 | D26: credit | E26: 910226 | G26: 618 | H26: =SUM(G26*1.14975) -> 710.5455 | K26: mi-juin
A27: 43920 | B27: danielle salvail | C27: =SUM(H27*0.3) -> 86.23125 | D27: credit | E27: 970292 | G27: 250 | H27: =SUM(G27*1.14975) -> 287.4375 | K27: fin juillet
A28: 43920 | B28: diane amyot | C28: =SUM(H28*0.3) -> 189.70875 | D28: credit | E28: 908400 | G28: 550 | H28: =SUM(G28*1.14975) -> 632.3625 | K28: mi-juin
A29: 43920 | B29: carl labonté | C29: =SUM(H29*0.3) -> 160.39013 | D29: depot | E29: 957782 | G29: 465 | H29: =SUM(G29*1.14975) -> 534.63375 | K29: mi-juin
A30: 43920 | B30: claude beauvais | C30: =SUM(H30*0.3) -> 137.97 | D30: depot | E30: 904442 | G30: 400 | H30: =SUM(G30*1.14975) -> 459.9 | K30: mi-juin
C31: =SUM(H31*0.3) -> 0 | H31: =SUM(G31*1.14975) -> 0
C32: =SUM(H32*0.3) -> 0 | H32: =SUM(G32*1.14975) -> 0
C33: =SUM(H33*0.3) -> 0 | H33: =SUM(G33*1.14975) -> 0
C34: =SUM(H34*0.3) -> 0

Sheet VENTE AXEL
A1: Date | B1: Valeur dépot | C1: Client | D1: Type paiement | E1: #contrat | G1: Valeur contrat | H1: Valeur après taxes | I1: Upsell | K1: Date de rappel production
A2: 43917 | B2: 86.23 | C2: Johanne Boudreau | D2: Interac | E2: 923019 | F2: jhnnboudreau@gmail.com | G2: 250 | H2: 287.44 | K2: mi juin
C3: Lucette | F3: lulugou
A4: 43917 | B4: 54.79 | C4: Réjean Ménard | D4: Crédit | E4: 923019 | G4: 158.85 | H4: 182.64 | K4: fin mai
A5: 43917 | B5: 39.67 | C5: Lisa Claveau | D5: Interac | E5: 927556 | F5: bolduc9747@gmail.com | G5: 115 | H5: 132.67 | K5: fin mai
A6: 43918 | B6: 15.52 | C6: Sylvain Lanoie | D6: Interac | E6: 915763 | F6: sylvainlanoie@hotmail.com | G6: 45 | H6: 51.74

Sheet VENTE VINCENT LAVOIE
A1: Date | B1: Client | C1: Valeur dépot | D1: Type paiement | E1: #contrat | G1: Valeur contrat | H1: Valeur après taxes | I1: Upsell | K1: Date de rappel production
A2: 43920 | B2: Harry Turnbull | C2: 110.16 | D2: Dépot l'an passé | E2: 8582 | G2: 290.39 | H2: 333.88 | I2: 0 | K2: mi-juin
A3: 43920 | B3: Maria Adonna | C3: 162.46 | D3: Crédit | E3: 987421 | G3: 471 | H3: 541.53 | I3: 0 | K3: mi-juin
A4: 43920 | B4: Sylvie Montero | C4: 137.52 | D4: Crédit | E4: 926778 | G4: 398 | H4: 458.41 | I4: 0 | K4: mi-juin
A5: 43920 | B5: Julie Tremblay | C5: 55.02 | D5: Crédit | E5: 904155 | G5: 159.5 | H5: 183.48 | I5: 0 | K5: Plus tot possible
A6: 43922 | B6: Stephane Gagnon | C6: 75.88 | D6: Credit | E6: 945238 | G6: 220 | H6: =G6*1.14975 -> 252.945 | I6: 0 | K6: juin

Sheet VENTE ERIKA
A1: Date | B1: Client | C1: Valeur dépot | D1: Type paiement | E1: #contrat | G1: Valeur contrat | H1: Valeur après taxes | I1: Upsell | K1: Date de rappel production
A2: 43913 | B2: Hélène Parenteau | C2: 51,60$ | D2: Crédit | E2: 948510 | G2: 149.6 | H2: 172,00$ | K2: rappeler pour lui offrir une date
A3: 43914 | B3: Johane Leclerc | C3: 39,66$ | D3: Credit | E3: 935504 | G3: 115 | H3: 132.22$
A4: 43914 | B4: Judith Bergeron | C4: 29,74$ | D4: credit | E4: 916771 | G4: 86.23 | H4: 99.14$
A5: 43914 | B5: Melanie Dubois | C5: 71,78$ | D5: credit | E5: 904274 | G5: 208.1 | H5: 239.27$
A6: 43915 | B6: Stephanie richard | C6: 99,88$ | D6: crédit | E6: 985624 | G6: 289.57 | H6: 332,95$ | K6: 5 juin et 4 octobre
A7: 43915 | B7: Genevieve Guillemette | C7: 67,73$ | D7: Crédit | E7: 938732 | G7: 196.35 | H7: 225,75$ | K7: 1er juillet
A8: 43916 | B8: Yvan Choquette | C8: 56,91$ | D8: Crédit | E8: 997500 | G8: 165 | H8: 189,71$ | K8: 43983

Sheet ESTIMATIONS
A1: Michel Plourde | B1: billy Thibodeau | C1: --> Flavien
A2: Gerald Belanger | B2: billy Thibodeau | C2: --> Flavien
A3: Tamara Kradaphole | B3: Sylvestre Erlin | C3: teddy | D3: crossbooking
A4: Tom Paul | B4: Isaac Safari | C4: Chloée | D4: pas confiance au tel
A5: Bernard Villeneuve | B5: jerome Cantin | C5: chloée | D5: Insatisfsait des travaux
A6: Bayley Gwen | B6: jerome Cantin | C6: Chloée | D6: Pas confiance au tel- pas email
A7: Joel AUBERT | B7: jerome Cantin | C7: Chloée | D7: Veut rencontrer le nouvel entrepreneur
A8: Guy Reny | B8: jerome Cantin | C8: Chloée | D8: lavage automne pas recu + mauvais service= veut rencontrer entrepreneur
A9: Richarde Ganza | B9: jerome Cantin | C9: Chloée | D9: veut pas donner carte
A10: helene arbour | B10: Jerome Cantin | C10: Chloée | D10: veut pas donner carte
A11: Jean Giasson | B11: Jerome Cantin | C11: Chloée | D11: veut pas donner carte
A12: Ramy Bakar | B12: Isaac Saffari | C12: --> Flavien | D12: VEUT PAS DONNER SON MAIL
A13: Sylvie de Grandmont | B13: Justin Champagne | C13: Paul | D13: ne veut pas donner sa carte
A14: Mario Tassé | B14: Étienne Ugnat-Laurin | C14: clem | D14: pas confiance au téléphone
... A20: Annick Bergeron | B20: Jerome Cantin | C20: Chloée | D20: veut se refaire estimer
A21: Diane Belanger | B21: Erlin Sylvestre | C21: Flavie | D21: crossbooking | F21: 20$
A22: Pierre Ouellette | B22: Christophe Couture | D22: Veut rencontrer le nouvel entrepreneur
A23: Claude Delanauze | B23: Etienne Ugnat-Laurin | C23: clem | D23: ne veut pas donner de dépot et veut avoir son lavage en mai...
A24: Denise PLante | B24: billy Thibodeau | C24: Paul | D24: Ne veut pas donner sa carte
A25: Pascale Drolet | B25: Alek Averill | C25: Flavie | D25: crossbooking (rendez-vous à séduler lorsque la situation du COVID-19 sera règlée

Sheet VENTE DANIELA
A1: Date | B1: Client | C1: Valeur dépot | D1: Type paiement | E1: #contrat | G1: Valeur contrat | H1: Valeur après taxes | I1: Upsell | K1: Date de rappel production | M1: #confirmation
A2: 43908 | B2: Françoise Bouffière | C2: 94.85 | D2: credit | E2: 901436 | G2: 275 | H2: 316.18
A3: 43908 | B3: Johanne Lafrance | C3: 47.05 | D3: crédit | E3: 976381 | G3: 136.4 | H3: 156.83
A4: 43908 | B4: Mireille Noel | C4: 56.91 | D4: Crédit | E4: 924566 | G4: 165 | H4: 189.71
A5: 43909 | B5: Mary-Lyne Roc | C5: 44.73 | D5: credit | E5: 971107 | G5: 129.69 | H5: 149.11
A6: 43909 | B6: France Saint-Pierre | C6: 68.3 | D6: credit | E6: 994250 | G6: 198 | H6: 227.65
A7: 43909 | B7: Annette Renaud | C7: 45.53 | D7: credit | E7: 994250 | G7: 132 | H7: 151.77
A8: 43909 | B8: Brigitte Faucher | C8: 103.66 | D8: credit | E8: 978395 | G8: 300.52 | H8: 345.52 | I8: 170
A9: 43909 | B9: Elise Desmarteau | C9: 54.13 | D9: credit | E9: 932122 | G9: 156.94 | H9: 180.44
A10: 43910 | B10: Daniel Summers Lépine | C10: 69.56 | D10: credit | E10: 987879 | G10: 201.66 | H10: 231.86
B11: Nicole Denault | C11: 56.91 | D11: credit | E11: 998060 | G11: 165 | H11: 189.71
B12: Claire Leger | C12: 58.05 | D12: credit | E12: 911088 | G12: 168.3 | H12: 193.5
G13: 2028.51
A14: 43913 | B14: Patrick Tremblay | C14: aucun, preuve de paye de l'année dernière | E14: 935332 | G14: 44.55 | H14: 51,22$
B15: Nadia Taria | C15: 37.94 | D15: credit | E15: 964628 | G15: 110 | H15: 126.47
B16: Celia Greenwood | C16: 37.94 | D16: credit | E16: 949988 | G16: 110 | H16: 126.47 | M16: 8QGXS9K35KSRM
B17: Arnold Ludwig | C17: 97.43 | D17: credit | E17: 964861 | G17: 282.46 | H17: 324.76
B18: Cecile Cyr | C18: 38.99 | D18: credit | E18: 936216 | G18: 113.03 | H18: 129.95
B19: Claire Lauzon | C19: 104.15 | D19: credit | E19: 957783 | G19: 301.95 | H19: 347.17
B20: Ilinca Ghibu | C20: 92.78 | D20: credit | E20: 908638 | G20: 269 | H20: 309.28
B21: Claire Castonguay | C21: 68.29 | D21: credit | E21: 910621 | G21: 197.98 | H21: 227.63
B22: Josée Bérubé | C22: 135,07 dépôt en attente | D22: credit | E22: 938751 | G22: 191 | H22: 450.24
A23: 43914 | B23: Julie DiFruscia | C23: dépôt la même journée de travail 84,51 | E23: 979330 | G23: 245 | H23: 281.69
B24: Gilles Chartier | C24: 74.62 | D24: credit | E24: 997271 | G24: 216.34 | H24: 248.73
B25: Sebastien Perreault | C25: 106.24 | D25: credit | E25: 935221 | G25: 308 | H25: 354.12
B26: Carole Barlow | C26: 98.3 | D26: credit | E26: 940265 | G26: 342 | H26: 393.21
B27: Miguel Brod / Valerie Lapalme | C27: 127.86 | D27: credit | E27: 970156 | G27: 370.7 | H27: 426.21
B28: Karine Brodeur | C28: 97.89 | D28: credit | E28: 907071 | G28: 283.8 | H28: 326.3
B29: Caroline Neault | C29: 101.87 | D29: credit | E29: 963932 | G29: 295.35 | H29: 339.58
A30: 43915
A31: 43916 | B31: Roger Boudreau | C31: 13.28 | D31: credit | E31: 942362 | G31: 38.5 | H31: 44.27
B32: Rachel Geoffrion | C32: 47.43 | D32: credit | E32: 972502 | G32: 137.5 | H32: 158.09
B33: Natalia Koszegi | C33: 120.54 | D33: credit | E33: 993564 | G33: 349.47 | H33: 401.8
A34: 43918 | B34: Karen O Grady | C34: 102.44 | D34: credit | E34: 949153 | G34: 297 | H34: 341.48
B35: Sophie Fortin | C35: 72.05 | D35: credit | E35: 952685 | G35: 208.9 | H35: 240.18
B36: Nadine Côté | C36: 40.82 | D36: credit | E36: 910077 | G36: 118.35 | H36: 136.07
B37: Frederic Jourdain | C37: 78.13 | D37: credit | E37: 974929 | G37: 226.5 | H37: 260.42
B38: Gina Boucher | C38: 34.34 | D38: credit | E38: 900163 | G38: 99.55 | H38: 114.46
B39: Frederic Landry | C39: 84.99 | D39: credit | E39: 909079 | G39: 246.39 | H39: 283.29
B40: Denis Parent | C40: 44.11 | D40: credit | E40: 954862 | G40: 127.87 | H40: 147.02
B41: Line bérubé | C41: 54.26 | D41: credit | E41: 930453 | G41: 157.3 | H41: 180.86
A43: 43920 | B43: Eric Laplante | C43: 58.64 | D43: credit | E43: 944496 | G43: 170 | H43: 195.46
B44: Patrice Bergeron | C44: 51.74 | D44: credit | E44: 971015 | G44: 150 | H44: 172.46
A45: 43921 | B45: Melanie Lessard | C45: 75.88 | D45: credit | E45: 921412 | G45: 220 | H45: 252.95
A46: 43922 | B46: Bernard Cyr | C46: 94.85 | D46: credit | E46: 946704 | G46: 275 | H46: 316.18
B47: Anne Little | C47: 30.35 | D47: credit | E47: 967753 | G47: 88 | H47: 101.18
B48: Amélia Roy | C48: 64,69 par chèque | D48: cheque | E48: 977805 | G48: 187.55 | H48: 215.64
B49: Jean-Marie Ngounou | E49: 988556 | G49: 107.25 | H49: 123.31
A50: 43923 | B50: Auguste/Chevalier Berthilde/Joseph Dieumane | E50: 995186 | G50: 410 | H50: 471.4
B51: Marie-andré Parent | C51: 72.43 | D51: credit | E51: 942571 | G51: 210 | H51: 241.45
B52: Gaetane Tremblay | C52: 28,46 par chèque | D52: cheque | E52: 921340 | G52: 82.5 | H52: 94.85
A53: 43924 | B53: Marie-Line Gagnon | C53: 100.03 | D53: credit | E53: 906653 | G53: 290 | H53: 333.43
B54: Linda Anderson | C54: 275.94 | D54: credit | E54: 904825 | G54: 800 | H54: 919.8
B55: Sébatien Beaulieu *2018* | C55: 113.83 | D55: credit | E55: 998096 | G55: 330 | H55: 379.42
A56: 43927 | B56: Girard Linda *2018* | C56: par cheque 78,92 | E56: 997602 | G56: 228.8 | H56: 263.06
A57: 43929 | B57: Paul Scott | C57: 151.01 | D57: credit | E57: 934056 | G57: 437.8 | H57: 503.36
B58: Suzanne Lafleur | C58: 151.01 | D58: credit | E58: 979604 | G58: 437.8 | H58: 503.36
A59: Da

Sheet VENTES CLEMENTINE
A1: Date | B1: Client | C1: Valeur dépot | D1: Type paiement | E1: #contrat | G1: Valeur contrat | H1: Valeur après taxes | I1: Upsell | K1: Date de rappel production
A2: 43906 | B2: Rania Bouabdo | C2: 61.6 | D2: credit | E2: 957423 | G2: 178.59 | H2: $205,33 | K2: dernière de mai
A3: 43906 | B3: Claude Mailhot | C3: 138.96 | D3: credit | E3: 957423 | G3: 402.88 | H3: 463.21 | K3: vers 20 mai si possible
A4: 43906 | B4: Danielle Marcil | C4: 138.77 | D4: credit | E4: 991261 | G4: 402.32 | H4: 462.57 | K4: fin mai
A5: 43906 | B5: Jean-Claude Perrault | C5: 292.15 | D5: credit | E5: 942174 | G5: 847 | H5: 973.84 | I5: 282 | K5: fin mai et 2e au mois
G6: =SUM(G2:G5) -> 1830.79 | H6: =SUM(H2:H5) -> 1899.62
A7: 43911 | B7: Sofia Cistellini | C7: 164.87 | D7: credit | E7: 914966 | G7: 478 | H7: 549.58 | K7: mi-mai
A8: 43911 | B8: Noémie Desmeules | C8: 90.11 | D8: credit | E8: 912122 | G8: 261.25 | H8: 300.37 | K8: juin
G9: =SUM(G7:G8) -> 739.25 | H9: =SUM(H7:H8) -> 849.95
A10: 43912 | B10: Vincent Paradis | C10: 225.58 | D10: credit | E10: 927915 | G10: 654 | H10: 751.94 | K10: fin mai
A11: 43912 | B11: François Vallières | C11: 174.88 | D11: credit | E11: 993618 | G11: 507 | H11: 582.92 | K11: juin
G12: =SUM(G10:G11) -> 1161 | H12: =SUM(H10:H11) -> 1334.86
G13: 7462.08
A14: 43913 | B14: André St-Pierre | C14: 72.43 | D14: credit | E14: 937333 | G14: 210 | H14: 241.45 | K14: juin Ext seulement en premier, 2e fin septembre
G15: =SUM (G14) -> 210 | H15: =SUM(H14) -> 241.45
A16: 43914 | B16: Marc Fortier | C16: 71.23 | D16: credit | E16: 972397 | G16: 206.5 | H16: 237.42 | K16: mi-mai
A17: 43914 | B17: Audrey Tam | C17: 70.15 | D17: virement intérac | E17: 933517 | G17: 61.01 | H17: 70.15 | K17: juin int/ext (gratuit) septembre ext
A18: 43914 | B18: Michelle Corneau | C18: 59.67 | D18: credit | E18: 938449 | G18: 173 | H18: 198.91 | K18: fin mai
A19: 43914 | B19: Johanne Bérubé | C19: 103.48 | D19: credit | E19: 918946 | G19: 300 | H19: 344.93 | K19: début juin
G20: =SUM (G16:G19) -> 740.51 | H20: =SUM(H16:H19) -> 851.41
A21: 43918 | B21: Josée Vidal | C21: 125.9 | D21: credit | E21: 916883 | G21: 365 | H21: 419.66 | K21: début juin - NE PAS OUBLIER LA PERCHE
A22: 43918 | B22: Isabelle Denis | C22: 94.85 | D22: virement intérac | E22: 968314 | G22: 275 | H22: 316.18 | K22: début juin
G23: =SUM(G21:G22) -> 640 | H23: =SUM(H21:H22) -> 735.84
A24: 43919 | B24: Louise Lalancette | C24: 44.84 | D24: virement intérac | E24: 934912 | G24: 130 | H24: 149.47 | K24: fin mai
A26: 43922 | B26: Yannick Bazin | C26: 79.16 | D26: credit | E26: 967313 | G26: 229.5 | H26: 263.87 | K26: haies: fin juin
G27: =SUM(G26) -> 229.5 | H27: =SUM(H26) -> 263.87
A28: 43925 | B28: Jean-Luc Demers | C28: pas de dépôt | E28: 904157 | G28: 307.63 | H28: 353.01 | K28: début juin
A29: 43925 | B29: France Rodier | C29: 98.3 | D29: credit | E29: 965632 | G29: 285 | H29: 327.68 | K29: haies: fin juin
A30: 43925 | B30: Robert Ladouceur | C30: 47.43 | D30: credit | E30: 900126 | G30: 137.5 | H30: 158.09 | K30: fin mai
G31: =SUM(G28:G30) -> 730.13 | H31: =SUM(H28:H30) -> 838.78
A32: 43926 | B32: Martine Tanguay | C32: 103.48 | D32: credit | E32: 951290 | G32: 300 | H32: 344.93 | K32: haies: fin juin la haie de devant faire les 3côtés!!
A33: 43926 | B33: Martine Tanguay | C33: 83.13 | D33: credit | E33: 980265 | G33: 241 | H33: 277.09 | K33: début juin
A34: 43926 | B34: Sylvain Caron | C34: 144.87 | D34: credit | E34: 917877 | G34: 420 | H34: 482.9 | K34: début juin
G35: =SUM(G32:G34) -> 961 | H35: =SUM(H32:H34) -> 1104.92
A36: 43927 | B36: Michel Bilodeau | C36: 75.88 | D36: credit | E36: 906912 | G36: 220 | H36: 252.95 | K36: début juin
A37: 43927 | B37: michel boulet | C37: 41.74 | D37: credit | E37: 918662 | G37: 121 | H37: 139.12 | K37: début juin
G38: =SUM(G36:G37) -> 341 | H38: =SUM(H36:H37) -> 392.07
A39: 43928 | B39: Maryse Brisson | C39: 62.09 | D39: virement intérac | E39: 966738 | G39: 180 | H39: 206.96 | K39: début juin AVANT LES VACANCES DE LA CONSTRUCTION
A40: 43928 | B40: Caroline Gendron | C40: 84.51 | D40: credit | E40: 937987 | G40: 245 | H40: 281.69 | K40: haies: fin juin
A41: 43928 | B41: Patrick Bertrand | C41: 38.48 | D41: credit | E41: 911399 | G41: 111.56 | H41: 128.27 | K41: haies: fin juin
A42: 43928 | B42: Jean-François Sarrazin | C42: 149.87 | D42: pas confirmé, rappel pour demain mais va prendre | E42: 1 | G42: 434.5 | H42: 499.57
G43: =SUM(G39:G42) -> 971.06 | H43: =SUM(H39:H42) -> 1116.49
A45: 18-04 | B45: stephane jacques | C45: 84.51 | D45: credit | E45: 991799 | G45: 245 | H45: 281.69 | K45: voisin de caroline gendron donc faire en même temps
A46: 18-04 | B46: Robert Nadeau | C46: 37.94 | D46: credit | E46: 910258 | G46: 110 | H46: 126.47 | K46: fin mai
G47: =SUM(G45:G46) -> 355 | H47: =SUM(H45:H46) -> 408.16
A48: 19-04 | B48: René Massé | C48: 108.65 | D48: chèque | E48: 998222 | G48: 315 | H48: 362.17 | K48: fin juin
G49: =SUM(G48) -> 315 | H49: =SUM(H48) -> 362.17

Sheet VENTE PL
A1: Date | B1: Client | C1: Valeur dépot | D1: Type paiement | E1: #contrat | G1: Valeur contrat | H1: Valeur aprés taxes | I1: Upsell | K1: Date de rappel production
B2: andree Lambert | C2: 174.52 | D2: credit | E2: 973518 | G2: 505.98 | K2: 43997
B3: Cécile richard | C3: 124.17 | D3: crédit | E3: 911872 | G3: 380 | K3: 43997
B4: Yves brunelle | C4: 125.21 | D4: crédit | E4: 973139 | G4: 363 | K4: 43997
G5: 1248.98
A6: 43914 | B6: Lucielle dufour | C6: 163.34 | D6: crédit | E6: 952715 | G6: 473.55 | K6: 44013
B7: Esther Patry Michaud | C7: 67.16 | D7: crédit | E7: 937578 | G7: 194.7 | K7: 43997
B8: Marie Simard | C8: 166.04 | D8: crédit | E8: 972934 | G8: 481.39 | K8: 43997
A9: Client pas rentrer dans RG | B9: louis desprès | C9: 249.28 | D9: crédit | E9: bug RG | G9: 722.7 | K9: 43997 | L9: YWGTVRH4KN2R0
B10: André fleury | C10: 51.22 | D10: crédit | E10: 958559 | G10: 148.5 | K10: 44089
B11: Annie-Claude Jolicoeur | C11: 75.88 | D11: crédit | E11: 948763 | G11: 220 | K11: 44012
B12: Jean noel brassard | C12: 76.83 | D12: crédit | E12: 957601 | G12: 222.75 | K12: 43966
B13: Pascal Azoulai | C13: 78.47 | D13: crédit | E13: 964305 | G13: 227.5 | K13: 43997
B14: Suzanne Fortin | C14: 43.12 | D14: Crédit | E14: 987942 | G14: 125 | K14: 43983
G15: 2816.09
A16: 43915 | B16: Josée Larouche | C16: 86.23 | D16: crédit | E16: 975131 | G16: 250 | K16: 43966
B17: Catherine Belisle | C17: 86.23 | D17: crédit | E17: 983479 | G17: 250 | K17: 43997
B18: Nicole Michaud | C18: 110.38 | D18: crédit | E18: 945190 | G18: 320 | K18: 43966
B19: Juliet Kemp | C19: 37.94 | D19: crédit | E19: 923279 | G19: 110 | K19: 43997
B20: Juliet Kemp | C20: 40.36 | D20: crédit | E20: 914992 | G20: 117 | K20: 43997
B21: francois Lessard | C21: 328.97 | D21: credit | E21: 971444 | G21: 953.75 | K21: 43981
B22: Ginette Landry | C22: 41.36 | D22: credit | E22: 972277 | G22: 120 | K22: 43997
B23: Paule Delisle | C23: 49.67 | D23: credit | E23: 953701 | G23: 144 | K23: 43997
B24: andrée morin | C24: 94.85 | D24: credit | E24: 907263 | G24: 275 | K24: 43997
B25: nicole demers | C25: 25.87 | D25: crédit | E25: 933881 | G25: 75 | K25: 43997
B26: Maxime bergeron | C26: 70.71 | D26: credit | E26: 901208 | G26: 205 | K26: 43997
B27: maude berger | C27: 51.74 | D27: credit | E27: 906429 | G27: 150 | K27: 43997
B28: Paul dandois | C28: 174.53 | D28: credit | E28: 936617 | G28: 506 | K28: 43997
B29: Jean claude corminer | C29: 170.74 | D29: credit | E29: 901493 | G29: 495 | K29: 43997
B30: Myriam Lacasse | C30: 245.67 | D30: credit | E30: 963056 | G30: 712 | K30: 43997
B31: guy sansfacon | C31: 286.29 | D31: credit | E31: 929169 | G31: 830 | K31: 43997
B32: Manon Bilodeau | C32: 185.57 | D32: credit | E32: 992833 | G32: 538 | K32: 43997
B33: sonia gasse | C33: 125.64 | D33: credit | E33: 997480 | G33: 364.25 | K33: 43997
B34: nathalie ouellette | C34: 89.68 | D34: credit | E34: 906211 | G34: 260 | K34: 43997
B35: richard grégoire | C35: 96.58 | D35: credit | E35: 966901 | G35: 280 | K35: 43997 | L35: estimation QE | M35: 10$
B36: chantale thériault | C36: 413.22 | D36: credit | E36: 907104 | G36: 1198 | K36: 43966
B37: sylvie legrand | C37: 72.43 | D37: credit | E37: 946772 | G37: 210 | K37: 43952
B38: christine lavoie | C38: 277.66 | D38: credit | E38: 924467 | G38: 805 | K38: 43952
G39: 9168
A40: 43916
B41: Nancy Twedelle | C41: 413.91 | D41: credit | E41: 988242 | G41: 1200 | K41: 43997
B42: marie eve roger | C42: 106.93 | D42: credit | E42: 921572 | G42: 310 | K42: 43997
B43: Tommy rodrigue | C43: 82.78 | D43: credit | E43: 918695 | G43: 210 | K43: 43966
B44: Pascal Bouchard | C44: 144.87 | D44: credit | E44: 957447 | G44: 420 | K44: 43966
B45: Francois Aumond | C45: 404.82 | D45: credit | E45: 929231 | G45: 1173.65 | K45: 43966
B46: Patrick Samson | C46: 34.49 | D46: credit | E46: 907280 | G46: 100 | K46: 43982
B47: annick ouellet | C47: 150.14 | D47: credit | E47: 993825 | G47: 435 | K47: 43997
B48: audrey bouchard | C48: 74.16 | D48: credit | E48: 990310 | G48: 215 | K48: 43997
B49: martin boucher | C49: 323.19 | D49: credit | E49: 915241 | G49: 937 | K49: 43983
B50: martin boiteau | C50: 120.72 | D50: credit | E50: 918252 | G50: 350 | K50: 43997
B51: andre theberge | C51: 89.68 | D51: credit | E51: 959155 | G51: 260 | K51: 43997
B52: Michel Fournier | C52: 137.97 | D52: credit | E52: 916230 | G52: 400 | K52: 43997
B53: Remy Dutil | C53: 93.13 | D53: credit | E53: 925709 | G53: 270 | K53: 43997
B54: yves tessier | C54: 103.48 | D54: credit | E54: 936982 | G54: 300 | K54: 43997
B55: Jean sébastien landry | C55: 115.55 | D55: credit | E55: 907376 | G55: 335 | K55: 43997
B56: Rene rivard | C56: 72.43 | D56: credit | E56: 955325 | G56: 210 | K56: 43997 | L56: approuvé par Joé
B57: Christian genest | D57: virement interac | G57: 735
B58: Francois dubé | C58: 253.52 | D58: credit | E58: 963298 | G58: 735 | K58: 43997
B59: Patrick lévesque | C59: 171.08 | D59: credit | E59: 906974 | G59: 496 | K59: 43997
G60: =SUM(G41:G59) -> 9091.65 | K60: 43997
A62: 43917 | D62: credit
B63: Grant vandermor | C63: 251.8 | D63: credit | E63: 900422 | G63: 735 | K63: 43997
B64: Daneil Duquet | C64: 120.72 | D64: credit | E64: 986451 | G64: 350 | K64: 43997
B65: Nancy Ouei | C65: 100.03 | D65: virement | G65: 290 | K65: 43997
B66: Carl Perron | C66: 65.54 | D66: credit | E66: 925845 | G66: 190 | K66: 43997
B67: Maryse Bégin | C67: 72.43 | D67: credit | E67: 989235 | G67: 210 | K67: 43997
B68: Jean Pierre Grégoire | C68: 214.46 | D68: credit | E68: 923756 | G68: 621.75 | K68: 43997
B69: Denis Godbout | C69: 69.33 | D69: Chèque | E69: 970774 | G69: 201 | K69: 43997
B70: Louis dumont | C70: 84.51 | D70: credit | E70: 950196 | G70: 245 | K70: 43997
B71: Brian Blackburn | C71: 113.83 | D71: credit | E71: 917039 | G71: 330 | K71: 43997
B72: Luc Labonté | C72: 117.27 | D72: credit | E72: 968291 | G72: 340 | K72: 43997
B73: Jean Giroux | C73: 135.11 | D73: credit | E73: 902075 | G73: 392 | K73: 43997
B74: caroline bourgeois | C74: 191.76 | D74: credit | E74: 916014 | G74: 555.95 | K74: 43997
B75: Celine giguere | C75: 109.34 | D75: credit | E75: 967201 | G75: 317 | K75: 43997
B76: diane langlois | C76: 134.52 | D76: facture QBO | E76: 926698 | G76: 390 | K76: 43997
B77: syvlie langevin | C77: 89.68 | D77: credit | E77: 949319 | G77: 260 | K77: 43997
B78: gilbert laporte | C78: 108.29 | D78: credit | E78: 969064 | G78: 313.95 | K78: 43997
B79: cristelle fasano | C79: 108.65 | D79: credit | E79: 965894 | G79: 315 | K79: 43997
B80: ginette champagne | C80: 212.54 | D80: credit | E80: 919984 | G80: 616 | K80: 43997
B81: Younk Bernadette | C81: 145.69 | D81: credit | E81: 995951 | G81: 422.37 | K81: 43997
B82: Margaret Janiszewski | C82: 93.13 | D82: credit | E82: 933848 | G82: 270 | K82: 43997
B83: Chantale Boulet | C83: 94.51 | D83: credit | E83: 982359 | G83: 274 | K83: 43997
B84: marie eve beaulieu | C84: 106.93 | D84: credit | E84: 905454 | G84: 310 | K84: 43997
G85: =SUM(G63:G84) -> 7949.02 | J85: total semaine | K85: =SUM(G85+G60+G39+G15+G5) -> 30273.74
A87: 43920
B88: Véronique Turcotte | C88: 67.26 | D88: crédit | E88: 915265 | G88: 195 | K88: 43997
B89: michele harvey | C89: 46.56 | D89: crédit | E89: 967152 | G89: 135 | K89: 43997
B90: melanie fortin | C90: 48 | D90: crédit | E90: 919638 | G90: 139.16 | K90: 43997
B91: Céline Morrow | C91: 80.71 | D91: crédit | E91: 956314 | G91: 234 | K91: 43997
B92: Marie pascal fortin | C92: 167.82 | D92: crédit | E92: 946760 | G92: 486.55 | K92: 43997
B93: Marc girard | C93: 199.8 | D93: crédit | E93: 969786 | G93: 579.8 | K93: 43997
B94: Francois Julien | C94: 203.51 | D94: crédit | E94: 925028 | G94: 590 | K94: 43997
B95: Julie Brassard | C95: 94.85 | D95: crédit | E95: 971227 | G95: 275 | K95: 43997
B96: chantale dion | C96: 107.62 | D96: crédit | E96: 989210 | G96: 312 | K96: 43997
B97: alexandre grenier | C97: 89.51 | D97: crédit | E97: 932541 | G97: 259.51 | K97: 43997
B98: alain briseboise | C98: 82.78 | D98: crédit | E98: 920878 | G98: 240 | K98: 43997
B99: MBentounes | C99: 220.75 | D99: crédit | E99: 901040 | G99: 640 | K99: 43997
B100: Jean francois roy | C100: 182.81 | D100: crédit | E100: 973948 | G100: 530 | K100: 43997
B101: Philippe Tremblay | C101: client doit envoyer preuve de dépot 2019 | E101: 988026 | G101: 575 | K101: 43997
B102: Marie claude bolduc | C102: 137.97 | D102: crédit | E102: 930912 | G102: 400 | K102: 43997
...

Sheet VENTE JOHANNA
A1: date | B1: Client | C1: Valeur dépot | D1: Type paiement | F1: #contrat | H1: Valeur contrat | J1: Valeur aprés taxes | K1: Upsell | M1: Date de rappel production
A2: 03-17 | B2: Diane Leblanc | C2: 74.18 | D2: visa | F2: 915196 | G2: contrat envoye | H2: 215.05 | J2: 247.25 | M2: juin
A3: 03-17 | B3: Nancy Willams | C3: 79.68 | D3: credit | F3: 919940 | H3: 225.76
A4: 03-17 | B4: Pierre Roussel | C4: 73.79$ | D4: credit | F4: 944863 | H4: 209.07
A5: 03-17 | B5: Liza sutherland | C5: 138.49$ | D5: credit | F5: 903865 | H5: 392.39
A6: 03-17 | B6: Jocelyne Joly | C6: 110.03$ | D6: credit | F6: 987270 | H6: 311.75
A7: 03-17 | B7: georges courville | C7: 184.02 | D7: credit | F7: 913121 | H7: 521.4
A8: 03-17 | B8: jean lemay | C8: 65.05 | D8: credit | H8: 184.3
A9: 03-17 | B9: connie Rose | C9: 94.85 | F9: 930046 | H9: 268.74
A10: 03-19 | B10: Sarah Lachaine | C10: 83.47 | D10: credit | F10: 901857 | H10: 278.24 | I10: 319.91 | M10: MI-JUIN
A11: 03-19 | B11: Monique Laliberte | C11: 149.47$ | D11: credit | F11: 956835 | H11: 499.57
A12: 03-19 | B12: Michele Bier | C12: 40.47$ | D12: credit | F12: 956617 | H12: 134.91
A13: 03-19 | B13: Michel Castonguay | C13: 83.47$ | D13: credit | F13: 923716 | H13: 278.24
A14: 03-19 | B14: Suzanne Cormier | C14: 100.33 | D14: credit | F14: 939639 | H14: 334.24
A15: 03-19 | B15: Micheline Senne | C15: 103.10 | D15: credit | F15: 991151 | H15: 343.68
A16: 03-19 | B16: Linda Richer | C16: 140.38 | D16: credit | F16: 976411 | H16: 467.95
A17: 03-19 | B17: Isabelle Faucher | C17: 44.00 | D17: credit | F17: 941170 | H17: 146.71
A18: 03-19 | B18: Giselle Cossette | C18: 178.37$ | D18: credit | F18: 900627 | H18: 594.56
A19: 03-19 | B19: Joanne Camirand | C19: 177.76 | D19: credit | F19: 922643 | H19: 592.52
A20: 03-19 | B20: Gilles Montpetit | C20: 389.85$ | D20: credit | F20: 970514 | H20: 1298.15
A21: 03-20 | B21: Nadine Jammal | C21: 115.60 | D21: credit | F21: 973280 | H21: 385.34
A22: 03-20 | B22: Suzanne Lepine | C22: 81.57 | D22: credit | F22: 922469 | H22: 271.92
A23: 03-20 | B23: Gilles Tanguay | C23: 111.93 | D23: credit | F23: 913140 | H23: 317.13 | I23: 373.09
A24: 03-21 | B24: Veronique Girard | C24: 45.91$ | D24: credit | F24: 992079 | H24: 153.08
A25: 03-21 | B25: Suzie Pineault | C25: 98.08 | D25: credit | F25: 913261 | H25: 326.93
A26: 03-21 | B26: Pierre-Alexandre bouchard | C26: 177.88 | D26: credit | F26: 917990 | H26: 572.92
A27: 03-22 | B27: Yvette Vachon | C27: 221.48 | D27: credit | F27: 905672 | H27: 738.28
A28: 03-22 | B28: Luc Sauve | C28: 122.17$ | D28: credit | F28: 900894 | H28: 407.24
A29: 03-22 | B29: Ugo Demers | C29: 98.46$ | D29: credit | F29: 962158 | H29: 328.2
H30: 10798.27
A31: 03-23 | B31: Estelle Patenaude | C31: 106.24$ | D31: credit | F31: 944202 | H31: 354.12
A32: 03-23 | B32: Virginie ares-trepanier | C32: 60.71$ | D32: credit | F32: 525336 | H32: 202.36
A33: 03-23 | B33: Roch Laflamme | C33: 79.68 | D33: credit | F33: 979422 | H33: 265.59
A34: 03-23 | B34: Yves Fortin | C34: 94.00 | D34: credit | F34: 985018 | H34: 313.34
A35: 03-23 | B35: Venessa Brunette | C35: 37.75 | D35: credit | F35: 951350 | H35: 125.84
A36: 03-23 | B36: Steve Giroux | C36: 87.45$ | D36: credit | F36: 902687 | H36: 291.51
A37: 03-23 | B37: Sylvain Gagne | C37: 87.27 | D37: credit | F37: 922706 | H37: 290.89
H38: 1843.55
A39: 03-24 | B39: Andre Bisson | C39: 55.02 | D39: credit | F39: 919019 | H39: 183.39
A40: 03-24 | B40: Louise Bergeron | C40: 55.52 | D40: credit | F40: 909229 | H40: 185.08
A41: 03-24 | B41: Loraine Pilon | C41: 131.07 | D41: credit | F41: 909856 | H41: 436.91
A42: 03-24 | B42: Lise Picard | C42: 104.03 | D42: credit | F42: 934004 | H42: 346.76
A43: 03-24 | B43: Jean-Francois Banville | C43: 77.78 | D43: credit | F43: 949055 | H43: 259.27
A44: 03-24 | B44: Eve-Marie Ouelet | C44: 77.78 | D44: credit | F44: 982281 | H44: 259.27
H45: 450
A46: 03-24 | B46: Yolande Crevier | C46: 71.33 | D46: credit | F46: 931541 | H46: 237.76
A47: 03-24 | B47: Sylvie Do | C47: 62.60 | D47: credit | F47: 970514 | H47: 208.68
A48: 03-25 | B48: Lise Clich | C48: 74.68 | D48: credit | F48: 939898 | H48: 264.71
A49: 03-25 | B49: Vanessa Gauthier | C49: 34.49 | D49: credit | F49: 954051 | H49: 120
A50: 03-26 | B50: Serge Barrette | C50: 184.19 | D50: credit | F50: 906908 | H50: 613.97
A51: 03-26 | B51: Monique Parent | C51: 66.78 | D51: credit | F51: 972786 | H51: 222.59
A52: 03-26 | B52: Marie-Claude Durand | C52: 76.57 | D52: credit | F52: 984067 | H52: 255.24
A53: 03-26 | B53: Jean-Yves Rivard | C53: 59.67 | D53: credit | F53: 929240 | H53: 198.91
A54: 03-26 | B54: Gerard Gamache | C54: 65.54 | D54: credit | F54: 916051 | H54: 218.45
A55: 03-26 | B55: Denise Marquis | C55: 34.49 | D55: credit | F55: 993395 | H55: 139.3
A56: 03-27 | B56: Carl Boivin | C56: 137.15 | D56: credit | F56: 993565 | H56: 457.16
A57: 03-27 | B57: Luc Normandin | C57: 61.05 | D57: credit | F57: 927835 | H57: 203.51
A58: 03-27 | B58: Jacques Brand | C58: 64.61 | D58: credit | F58: 944866
A59: 03-30 | B59: Pierre Vallee | C59: 127.62 | D59: credit | F59: 906914 | H59: 425.41

Sheet VENTES CLEMENT
A1: Date | B1: Client | C1: Valeur dépot | D1: Type paiement | E1: #contrat | G1: Valeur contrat | H1: Valeur aprés taxes | I1: Upsell | K1: Date de rappel production
A2: 43907 | B2: Lucie Plourde | C2: 184.02$ | D2: interact | E2: 944609 | G2: 585 | H2: 613.39$ | I2: Lavage a pression | K2: Mai
A3: 45002 | B3: Martin Fortier | C3: 152.81 | D3: visa | E3: 910607 | G3: 443.03 | H3: 509.37$ | I3: vidage goutiere | K3: juin
A4: 45003 | B4: Andree Beaudet | C4: 84,59 $ | D4: visa | E4: 930600 | G4: 245.23 | H4: 281.96$ | K4: mai
A5: 43908 | B5: Atnae Lussier | C5: 92.96$ | D5: interact | E5: 927198 | G5: 269.5 | H5: 309.86$ | I5: elle voulait cette fois un lav int/ext | K5: juin
A6: 43908 | B6: Carole Fillion | C6: 57.10$ | D6: visa | E6: 957319 | G6: 165.55 | H6: 190.34$ | K6: Juin
A7: 43908 | B7: Francine Vezina | C7: 157.46$ | D7: MasterCard | E7: 943420 | G7: 456.5 | H7: 524.86$ | K7: Juillet
B8: Louise Leblanc | C8: 56.34 | D8: visa | E8: 908726 | G8: 148.5 | H8: 187.81$ | K8: Juin
B9: Jean-Marc Gagnon | C9: 44.25 | D9: visa | E9: 960380 | G9: 147.5 | H9: 169.6 | K9: Mai
B10: Alain Thauvette
A12: 43909 | B12: Antoine Groulx | C12: 239.03$ | D12: interact | E12: 908738 | G12: 693 | H12: 796.78$ | K12: Mai
A13: 43909 | B13: Elaine Belanger | C13: 118.58$ | D13: interact | E13: 900925 | G13: 343.78 | H13: 395.26$ | K13: Mai
A14: 43914 | B14: Jean Manseau | C14: 39.84$ | D14: interact | E14: 979338 | G14: 115.50$ | H14: 132.80$ | K14: Mai
A15: 43916 | B15: Stephane Turcot | C15: 98.1 | D15: interact | E15: 965744 | G15: 327$ | H15: 376$ | K15: Juin
A16: 43916 | B16: Dominic Bérubé | C16: 150$ | D16: interact | E16: 997799 | G16: 350$ | H16: 402.5$ | K16: mi-Juin
A17: 43916 | B17: Stéphanie Lapointe | C17: 84.6$ | D17: interact | E17: 966118 | G17: 282.24$ | H17: 324.6$ | K17: fin-Juin
G18: 3766.35

Sheet VENTE FRED
A1: Date | B1: Client | C1: Valeur dépot | D1: Type paiement | E1: #contrat | F1: Numéro confirmation | G1: Valeur contrat | H1: Valeur aprés taxes | I1: Upsell | K1: Date de rappel production
A2: 43912 | B2: Yves Mongeau | C2: 127.42 | D2: Crédit | E2: 981298 | G2: 388.85 | H2: 447.08 | I2: 0 | K2: Début-Juin
A3: 43913 | B3: Maryse st-martin | C3: 115.93 | D3: Crédit | E3: 904019 | G3: 336.11 | H3: 386.44 | I3: 0 | K3: Mi-juin
A4: 43913 | B4: Jean-Pierre Lefevre | C4: 49.55 | D4: Virement interac | E4: 906243 | G4: 143.71 | H4: 165.11 | I4: 0 | K4: Mi-juin
A5: 43913 | B5: Sam Delia | C5: 68.3 | D5: Crédit | E5: 955670 | G5: 220 | H5: 252.94 | I5: 0 | K5: Début-Juillet
A6: 43913 | B6: Jean-François Delade | C6: 71.03 | D6: Virement interac | E6: 947254 | G6: 228.8 | H6: 263.06 | I6: 0 | K6: Mi-Juin
A7: 43913 | B7: Evelyne Paquette | C7: 99.63 | D7: Crédit | E7: 981833 | G7: 320.93 | H7: 368.99 | I7: 0 | K7: Mi-jJuin
A8: 43913 | B8: Margeret Plante | C8: 152.53 | D8: Crédit | E8: 953756 | G8: 442.2 | H8: 508.42 | I8: 0 | K8: Début-Juin
A9: 43913 | B9: Diane Ferragne | C9: 104.86 | D9: Crédit | E9: 984965 | G9: 304 | H9: 349.52 | I9: 0 | K9: Début-Juin
G10: 2384.6
A11: 43914 | B11: Noelle Coursol | C11: 72.09 | D11: Crédit | E11: 976831 | G11: 209 | H11: 240.3 | I11: 0 | K11: Début-juin
A12: 43914 | B12: Alain gauvreau | C12: 139.35 | D12: Crédit | E12: 940050 | G12: 404 | H12: 464.5 | I12: 0 | K12: Début-Juin
A13: 43914 | B13: milène Rizcalla | C13: 91.06 | D13: Crédit | E13: 976831 | G13: 264 | H13: 303.53 | I13: 0 | K13: Début-Juin
A14: 43914 | B14: Dany Béland | C14: 175.91 | D14: Crédit | E14: 908993 | G14: 510 | H14: 586.37 | I14: 0 | K14: Fin- mai
A15: 43914 | B15: Dany Gauthier | C15: 184.53 | D15: Virement | E15: 961915 | G15: 535 | H15: 615.12 | I15: 0 | K15: Début-Juin
A16: 43914 | B16: Hélène béland | C16: 169.01 | D16: crédit | E16: 920174 | G16: 490 | H16: 563.38 | I16: 0 | K16: Début-Juin
A17: 43914 | B17: Johanne Quintal | C17: 200.54 | D17: Crédit | E17: 920352 | G17: 581.4 | H17: 668.46 | I17: 0 | K17: Début-Juin
A18: 43914 | B18: Michèle boisvert | C18: 211.09 | D18: Crédit | E18: 927126 | G18: 612 | H18: 703.65 | I18: 0 | K18: Début juin
G19: 3605.4
A20: 43915 | B20: Sylvestre Pierre | C20: 38.29 | D20: crédit | E20: 946533 | F20: TD0F5SSDGF3H4 | G20: 111 | H20: doit mettre contrat | I20: 0 | K20: Début juin
A21: 43915 | B21: Line laplante | C21: 75.98 | D21: crédit | E21: 92712 | F21: DKGAQME969X0M | G21: 220 | H21: 252.95 | I21: 0 | K21: Début juin
A22: 43915 | B22: Francois Michaud | C22: 91.06 | D22: crédit | E22: 954076 | F22: 8H8830M33CQD4 | G22: 264 | H22: 303.53 | I22: 0 | K22: Début juin
A23: 43915 | B23: Paul d'amboise | C23: 93.82 | D23: Crédit | E23: 917948 | F23: 2SEYPDPW6BHXA | G23: 272 | H23: 312.12 | I23: 0 | K23: début juin
A24: 43915 | B24: François Laroche | C24: 178.5 | D24: crédit | E24: 900665 | F24: 818TDAYC1YCRJ | G24: 517.5 | H24: 595 | I24: 0 | K24: Début-juin
B25: Andre bilodeau | C25: 137.97 | D25: virement | E25: 966964 | G25: 400 | H25: 459.6 | I25: 0 | K25: Mi-Juin
A26: 43915 | B26: Marc-andré benoit | C26: 86.58 | D26: crédit | E26: 974829 | F26: MWYD39NKG9PTJ | G26: 251 | H26: 288.59 | I26: 0 | K26: Début-juin
B27: anne julie racicot | C27: 82.78 | D27: virement | E27: 978610 | G27: 240 | H27: 275.94 | I27: 0 | K27: Début-juin
B28: ariane côté | C28: 77.61 | D28: crédit | E28: 984975 | F28: 3VK48M4YTXEB6 | G28: 225 | H28: 258.69 | I28: 0 | K28: Début-juin
B29: chantal fournier | C29: 128.14 | D29: virement | E29: 959018 | G29: 371.5 | H29: 427.13 | I29: 0 | K29: Début-juin
A30: 43915 | B30: Isabelle Gravel | C30: 99.34 | D30: Crédit | E30: 977184 | F30: ZKY5QTJ84T9NE | G30: 288 | H30: 331.34 | I30: 0 | K30: Début juin
A31: 43916 | B31: Jean-Claude Guedon | C31: 103.48 | D31: Crédit | E31: 973598 | F31: H3EZHE6W36R6W | G31: 300 | H31: 344.93 | I31: 0 | K31: Début Juin
A32: 43917 | B32: Éric Lemieux | C32: 156.6 | D32: virement | E32: 994959 | G32: 454 | H32: 521.99 | I32: 0 | K32: Fin-juin
A34: 43923 | B34: Benoit Pronovost | C34: 107.27 | D34: crédit | E34: 989764 | F34: RRK1K9TV5EW30 | G34: 311 | H34: 357.57 | I34: 0 | K34: Début-Juin
A35: 43923 | B35: Janet Salera | C35: 72.43 | D35: crédit | E35: 924461 | F35: BNJSGSEV53RMT | G35: 210 | H35: 241.55 | I35: 0 | K35: Mi-juin
A36: 43927 | B36: anne julie racicot | C36: 82.78 | D36: virement confirmé | E36: 978610 | G36: 240 | H36: 275.94 | I36: 0 | K36: Début-Juin
A37: 43927 | B37: Diane Chatigny | C37: 206.18 | D37: virement | E37: 971768 | G37: 597.75 | H37: 687.27 | I37: 0 | K37: Fin mai
A38: 43927 | B38: patricia lesieur | C38: 80.71 | D38: crédit | E38: 924479 | F38: VHG3J3C8P8S1G | G38: 234 | H38: 269.04 | I38: 0 | K38: Début-Juin
A39: 43928 | B39: juliette grenet | C39: 143.62 | D39: crédit | E39: 956322 | F39: VA4SD70D7T0VG | G39: 413.37 | H39: 478.72 | I39: 105.95 | K39: Début-juin
A40: 43928 | B40: bruno lavoie | C40: 124.17 | D40: crédit | E40: 916820 | F40: J6HTSCPWS8HRP | G40: 360 | H40: 413.91 | I40: 225 | K40: Début-juin
A41: 43928 | B41: violeta patzeva | C41: 172.15 | D41: crédit | E41: 969609 | F41: SAVJMPHDRAMAC | G41: 502 | H41: 577.17 | I41: 175 | J41: client 2018 (11%) | K41: Début-juin | L41: 11% comm
A42: 43928 | B42: vanessa lapierre | C42: 59.33 | D42: crédit | E42: 904308 | F42: YJDJB98S7C67G | G42: 172 | H42: 197.76 | I42: 0 | K42: Début-juin

Sheet VENTE ISAAK
A1: Date | B1: Client | C1: Valeur dépot | D1: Type paiement | E1: # Contrat | F1: # Confirmation | G1: Valeur contrat | H1: Valeur aprés taxes | I1: Upsell | J1: Date de rappel production
A2: 43916 | B2: Yannick Dupras | C2: 31.04 | D2: Credit | E2: 971851 | G2: 90 | H2: 103.47 | J2: Mi-Juin
A3: 43916 | B3: Marie-Claude Lefebvre | C3: 39.67 | D3: Credit | E3: 935798 | G3: 115 | H3: 132.22 | J3: Mi-Juin
A4: 43919 | B4: Carmen Goyette | C4: 48.29 | D4: Credit | E4: 996355 | G4: 140 | H4: 160.97 | J4: Mi-Juin
A5: 43919 | B5: Sylvie Bernier | C5: 60.36 | D5: Credit | E5: 940174 | G5: 175 | H5: 201.21 | J5: Septembre
A6: 43919 | B6: Natalie Lachance | C6: 55.19 | D6: Credit | E6: 946531 | G6: 160 | H6: 183.96 | J6: Fin Aout
A7: 43919 | B7: Jacques Ledoux | C7: 405.29 | D7: Credit | E7: 998824 | G7: 1175 | H7: 1350.96 | J7: Fin Aout | K7: PAIE 179$
A8: 43921 | B8: Paul Prevost | C8: 62.09 | D8: Credit | E8: 996416 | G8: 180 | H8: 206.96 | J8: Mi-Juin
A9: 43921 | B9: Stephane Fredette | C9: Aucun | D9: Credit | E9: 972598 | G9: 340 | H9: 390.92 | J9: Septembre
A10: 43921 | B10: Claude Binette | C10: 89.63 | D10: Credit | E10: 994667 | G10: 260 | H10: 298.93 | J10: Mi-Juin
A11: 43921 | B11: Claude Bourbonnais | C11: 86.23 | D11: Credit | E11: 994906 | G11: 250 | H11: 287.44 | J11: Mi-Juin
A12: 43921 | B12: Isabelle Madore | C12: 77.61 | D12: Credit | E12: 977558 | G12: 250 | H12: 258.69 | J12: Mi-Juin
A13: 43921 | B13: Charles Lafontaine | C13: 68.64 | D13: Credit | E13: 947092 | G13: 199 | H13: 228.80 | J13: Mi-Juin
A14: 43921 | B14: Anne-Marie Côté | C14: 63.81 | D14: Credit | E14: 969543 | G14: 185 | H14: 212.70 | J14: Mi-Juin
A15: 43921 | B15: Donald Marquis | C15: 232.82 | D15: Credit | E15: 968557 | G15: 675 | H15: 776.08 | J15: Mi-Juin
A16: 43921 | B16: Danny Dionne | C16: 55.19 | D16: Credit | E16: 979743 | G16: 160 | H16: 183.96 | J16: Mi-Juin
A17: 43923 | B17: Christiane Boisvert | C17: 51.74 | D17: Credit | E17: 972683 | G17: 150 | H17: 172.46 | J17: Debut Juin
A18: 43929 | B18: Philippe Gagnon | C18: 34.49 | D18: Credit | E18: 935272 | G18: 100 | H18: 114.98 | J18: Mi-Juin

Sheet VENTES MARC-ALEXANDRE
A1: Date | B1: Client | C1: Valeur dépot | D1: Numéro de confirmaiton | E1: Type paiement | F1: #contrat | H1: Valeur contrat | I1: Valeur aprés taxes | J1: Upsell | L1: Date de rappel production | M1: note
A2: 43906 | B2: Rene Fournier | C2: 98.33 | E2: credit | F2: 971357 | H2: 285 | I2: 327.75 | L2: mi mai
A3: 3h | B3: Sylvie Marceau | C3: 124.53 | E3: credit | F3: 917179 | H3: 380.5 | I3: 436.97 | L3: mi mai
B4: Isabelle Desrochers | C4: 134.46 | E4: credit | F4: 947102 | H4: 465.31 | I4: 534.99 | L4: mi mai
M5: dépôt envoyé par la poste
A6: 43908 | B6: Réjean Clouthier | C6: 134.95 | E6: cheque | F6: 955179 | H6: 410 | I6: 471.4
A7: 7h | B7: Lyne Chabot | C7: 121.22 | E7: credit | F7: 927334 | H7: 351.55 | I7: 408.85
B8: Suzanne leblanc | C8: 93.80 | E8: credit | F8: 927334 | H8: 286.5 | I8: 329.48
B9: Jeanne dumas | C9: 71.03 | E9: virement interac | F9: 994215 | H9: 263.06 | I9: 263.06
B10: Martine Jean | C10: 111.41 | E10: credit | F10: 994215 | H10: 323 | I10: 371.37
A11: 43909 | B11: Pauline McEniry | C11: 45.01 | E11: credit | F11: 939920 | H11: 130.5 | I11: 150.04
B13: Pierre-Francois Ricard | C13: 60.71 | E13: credit | F13: 939920 | H13: 176 | I13: 202.36
A14: 7h | B14: Paul Veces | C14: 81.86 | E14: credit | F14: 939920 | H14: 237.33 | I14: 272.86
B15: Pro-automation | C15: 102.44 | E15: credit | F15: 914862 | H15: 297 | I15: 341.48
B16: Florent Gaudrault | C16: 360.1 | E16: credit | F16: 922655 | H16: 1020.03 | I16: 1200.3
B17: Yves leroux | C17: 300.78 | E17: credit | F17: 922655 | H17: 872 | I17: 1002.59
B18: Marie-France Paré | C18: 206.96 | E18: credit | F18: 965465 | H18: 600 | I18: 689.85
A19: 43910 | B19: Josee danis | C19: 151.58 | E19: credit | F19: 934641 | H19: 439.55 | I19: 505.26
B20: Colette Lefort | C20: 375.62 | F20: 975579 | H20: 1089 | I20: 1252.08
B21: Caroline El-Khoury | C21: 182.12 | E21: credit | F21: 949517 | H21: 528 | I21: 607.07
B22: Elsa Gomez | C22: 212.95 | E22: credit | F22: 940085 | H22: 617.38 | I22: 709.84 | J22: 224.83
G23: Total | H23: 8771.71
A24: 43911 | B24: Hugues Gagné | C24: 151.58 | E24: credit | F24: 934641 | H24: 698.5 | I24: 803.1
B25: Sylvie Carpentier | C25: 111.51 | E25: credit | F25: 981776 | H25: 359.2 | I25: 413
B26: Ronald Gendron | C26: 134.18 | E26: credit | F26: 978201 | H26: 389 | I26: 447.26
B27: Michelle Labelle | C27: 260.76 | E27: credit | F27: 940218 | H27: 756 | I27: 869.21
B28: Louise Matte | C28: 103.48 | E28: credit | F28: 996757 | H28: 600 | I28: 689.86
B29: Mathieu Lahaye | C29: 133.83 | E29: credit | F29: 933941 | H29: 388 | I29: 446.1
A30: 43913 | B30: Patrice Roy | C30: 192 | D30: 8QGXS9K35KSRM | E30: credit | F30: 936350 | H30: 586.5 | I30: 674.33
B31: Maurice Doyon | C31: 361.06 | D31: F7B8EEWQZ3NHP | E31: credit | F31: 934988 | H31: 1046.78 | I31: 1203.54
B32: Maurice Lavoie | C32: 252.23 | D32: JF1B214PWRVY0 | E32: credit | F32: 972553 | H32: 734.16 | I32: 844.1
B33: Marie-Pier | C33: 171.02 | D33: THXHHHXXPM3B8 | E33: credit | F33: 920904 | H33: 495.83 | I33: 570.08
B34: sylvain Drouin | C34: 229.38 | D34: KZHRPH066YNK6 | E34: credit | F34: 984931 | H34: 665 | I34: 764.59
H35: 3528.27
A36: 43914 | B36: JF Couturier | C36: 0 | D36: Contrat signé et il a parlé à adrien | F36: 917994 | H36: 630 | I36: 724.34
B37: JF Couturier | C37: 0 | D37: Contrat signé et il a parlé à adrien | F37: 914135 | H37: 410 | I37: 471.40
B38: Maxine Raymond | C38: 165.81 | D38: ZQT0FN4YBX9SY | E38: credit | F38: 972722 | H38: 506 | I38: 581.78
B39: Suzanne Clement | C39: 117.28 | D39: MYCHSFNDTV6RE | E39: Credit | F39: 901658 | H39: 340 | I39: 390.92
B40: Marc bompoint | C40: 217.30 | D40: 4SC8DCHMSMBEW | E40: credit | F40: 944900 | H40: 630 | I40: 724.35
B41: Martin Bérubé | C41: 293.19 | D41: 5JE6ZDKGKE9JJ | E41: credit | F41: 926890 | H41: 850 | I41: 977.29
H42: 3366
A43: 43915 | B43: Joelle Ganguillet | C43: 37.94 | D43: NDQ1TFD9F924J | E43: credit | F43: 971437 | H43: 110 | I43: 126.47
B44: Jean-Francois Tassé | C44: 129.35 | D44: MY3M1QJ8TW4GG | E44: credit | F44: 996815 | H44: 375 | I44: 431.16
B45: Pascale Roy | C45: 86.23 | D45: Y55XQCBT2AXWM | E45: credit | F45: 913129 | H45: 250 | I45: 287.44
B46: Rodena Severe | C46: 146.16 | D46: E521QG3BZ88Z8 | E46: credit | F46: 983911 | H46: 423.75 | I46: 487.21
B47: Rodena Severe | C47: 213.62 | D47: 7PBRXV0EAFH4C | E47: credit | F47: 917078 | H47: 619.33 | I47: 712.07
B48: Sandra Campagna | C48: 90.14 | D48: PQG3J43RMV6X2 | E48: credit | F48: 972430 | H48: 261 | I48: 300.46
B49: Jeannette Bourget | C49: 166.60 | D49: cheque | E49: cheque | F49: 989113 | H49: 483 | I49: 555.32
B50: Julien Cardinal | C50: 171.08 | D50: KKBHVP2ZHQKVP | E50: credit | F50: 902013 | H50: 496 | I50: 570.28
B51: Guy Beauchamps | C51: 155.91 | D51: AT1FRMHPRSH66 | E51: credit | F51: 948314 | H51: 452 | I51: 519.69
H52: 573645
A53: 26-Mar | B53: Marc Gauthier | C53: 121.84 | D53: VYTXZY46BWEV8 | E53: credit | F53: 979878 | H53: 352.25 | I53: 406.15
B54: Sylvie cote | C54: 228.8 | D54: 2XGTCPVXYR2DR | E54: credit | F54: 904579 | H54: 663.33 | I54: 762.66
B55: Christian Genest | C55: 249.9 | D55: virement | E55: interac | F55: 952676 | H55: 724.5 | I55: 833
B56: Lara Bilodeau | C56: 257.83 | D56: AKJZ3D8FAQQK0 | E56: credit | F56: 978592 | H56: 747.5 | I56: 859.44
H57: 2487.58
A58: 03-27 | B58: Myriam Bourgault | C58: 193.167 | D58: HA40DDB6CVQ3Y | E58: credit | F58: 979534 | H58: 560 | I58: 643.86
B59: Christine Tremblay | C59: 179.57 | D59: WCH8KWZ8P10TT | E59: credit | F59: 935075 | H59: 520 | I59: 598.59
B60: Marie-Hélène Leboeuf | C60: 62.09 | D60: FY80FJVTHPYCC | E60: credit | F60: 924426 | H60: 180 | I60: 206.96
B61: Audrée Dorais | C61: 194.88 | D61: 28WP1HDBWT1PW | E61: credit | F61: 981796 | H61: 565 | I61: 649.61
A63: trouver contrat | E63: cheque | H63: 1078
A64: trouver contrat | E64: virement | H64: 170
A65: à vérifier avec PL | E65: cheque | H65: 132 | J65: probleme avec pierre-luc M | L65: il manque 594.16$ et 491.22$ si on ne compte que les depots credit.
H66: 3205
A67: 43937 | B67: Mireiller Borduas | C67: 77.36 | D67: Z46YZFN07HSW8 | E67: Credit | F67: 968251 | H67: 224.04 | I67: 257.59
A68: 43940 | B68: Christiane Dubreuil | C68: 103.48 | D68: EMWEBBB3YHQET | E68: credit | F68: 900551 | H68: 300 | I68: 344.92
A69: 43941 | B69: Michele Labelle | C69: 60 | D69: 7BQYDCETKSGNC | E69: credit | F69: 923273 | H69: 173.96 | I69: 200.02
B70: Nancy Dufour | C70: 52.43 | D70: 5CQJHSWR1V7Y2 | E70: credit | F70: 972898 | H70: 152 | I70: 174.76

Sheet Feuille 13

Sheet VENTES ClOEE
A1: Date | B1: Client | C1: Valeur dépot | D1: Type paiement | E1: #contrat | G1: Valeur contrat | H1: Valeur aprés taxes | I1: Upsell | K1: Date de rappel production
A2: 43915 | B2: Maryse Carignan | C2: 129 | D2: Crédit | E2: 16352 (913418) | G2: 374 | H2: 430.01 | I2: non | K2: Mi-Juin
A3: 43916 | B3: Denis Latulippe | C3: 174.53 | D3: Crédit | E3: 917034 | G3: $506,00 | H3: 581.77 | I3: non | K3: Mi-Juin
A4: 43916 | B4: Lyne Laurendeau | C4: 78.64 | D4: Crédit | E4: 999331 | G4: 228 | H4: 262.14 | I4: non | K4: Mi-Juin
A5: 43919 | B5: Marcos Balbinotti | C5: 54.27 | D5: Crédit | E5: 935654 | G5: 386.83 | H5: 180.89 | I5: non | K5: Mi-Juin
A6: 43919 | B6: Julie Saint-Arnaud | C6: 79.16 | D6: Crédit | E6: 909934 | G6: 229.5 | H6: 263.87 | I6: non | K6: Mi-Juin

Sheet VENTES ANTHONY
A1: Date | B1: Client | C1: Valeur dépot | D1: Type paiement | E1: #contrat | G1: Valeur contrat | H1: Valeur après taxes | I1: Upsell | K1: Date de rappel production
A2: 43913 | B2: Lise Cloutier | C2: 191.52 | D2: Crédit | E2: 986808 | G2: 555.25 | H2: =G2*1.14975 -> 638.39869 | I2: Non | K2: Début Juin

Sheet VENTES ÉMILE CÔTÉ
A1: Date | B1: Client | C1: Valeur dépot | D1: Type paiement | E1: #contrat | G1: Valeur contrat | H1: Valeur après taxes | I1: Upsell | K1: Date de rappel production

Sheet Sommaire
A1: Flavie | B1: Année | C1: Période | D1: Clementine | E1: Année | F1: Période | G1: Teddy | H1: Année | I1: Période | J1: Chloe | K1: Année | L1: Période | M1: Paul | N1: Année | O1: Période | P1: Autres | Q1: Année | R1: Période | S1: Amanda | T1: Année | U1: Prériode | V1: total annéee | W1: total semaine
A2: Nb. d'heures | B2: 38 | C2: 12 | E2: 51 | F2: 17 | H2: 21 | I2: 0 | K2: 27 | L2: 12 | N2: 22 | O2: 8 | Q2: 40 | R2: 12 | T2: 13 | U2: 13 | V2: =SUM(B2,E2,H2,K2,N2,Q2,T2) -> 212 | W2: =SUM(C2,F2,I2,O2,R2,U2) -> 62
A3: Ventes totales | B3: =SUM(VENTES!H4,VENTES!H5,VENTES!H7,VENTES!H8,VENTES!H9,VENTES!H18,VENTES!H19,VENTES!H20,VENTES!H22,VENTES!H27,VENTES!H29,VENTES!H32,VENTES!H38,VENTES!H39,VENTES!H44,VENTES!H45,VENTES!H47,VENTES!H53,VENTES!H56,VENTES!H96,VENTES!H99,VENTES!H102,VENTES!H104,VENTES!H106,VENTES!H108,VENTES!H112,VENTES!H131,VENTES!H133,VENTES!H136) -> 12589.998 | C3: =SUM(VENTES!H96,VENTES!H99,VENTES!H102,VENTES!H104,VENTES!H106,VENTES!H108,VENTES!H112,VENTES!H131,VENTES!H133,VENTES!H136) -> 5293.986 | E3: =SUM(VENTES!H3,VENTES!H15,VENTES!H16,VENTES!H17,VENTES!H41,VENTES!H78,VENTES!H79,VENTES!H80,VENTES!H87,VENTES!H91,VENTES!H93,VENTES!H98,VENTES!H101,VENTES!H109,VENTES!H126,VENTES!H130,VENTES!H134) -> 5558.5192 | F3: =SUM(VENTES!H91,VENTES!H93,VENTES!H98,VENTES!H101,VENTES!H109,VENTES!H126,VENTES!H130,VENTES!H134) -> 2994.88 | H3: =SUM(VENTES!H21,VENTES!H28,VENTES!H36,VENTES!H37,VENTES!H43,VENTES!H49,VENTES!H51,VENTES!H55,VENTES!H57,VENTES!H62,VENTES!H66,VENTES!H67,VENTES!H68) -> 3832.5815 | I3: 0 | K3: =SUM(VENTES!H26,VENTES!H33,VENTES!H35,VENTES!H42,VENTES!H50,VENTES!H54,VENTES!H58,VENTES!H63,VENTES!H64,VENTES!H65,VENTES!H107,VENTES!H110,VENTES!H111,VENTES!H113,VENTES!H116,VENTES!H117,VENTES!H118,VENTES!H119) -> 6556.2167 | L3: =SUM(VENTES!H107,VENTES!H110,VENTES!H111,VENTES!H113,VENTES!H116,VENTES!H117,VENTES!H118,VENTES!H119) -> 3964.66 | N3: =304.75+1845.41 -> 2150.16 | O3: =SUM(VENTES!H95,VENTES!H100,VENTES!H103,VENTES!H127,VENTES!H132) -> 704.28 | Q3: =SUM(VENTES!H6,VENTES!H88,VENTES!H82,VENTES!H81,VENTES!H76,VENTES!H75,VENTES!H74,VENTES!H60,VENTES!H52,VENTES!H48,VENTES!H40,VENTES!H34,VENTES!H30,VENTES!H120,VENTES!H121,VENTES!H129,VENTES!H135) -> 3954.2802 | R3: =SUM(VENTES!H120,VENTES!H121,VENTES!H129,VENTES!H135) -> 785.7 | T3: =U3 -> 1161.28 | U3: =SUM(VENTES!H92,VENTES!H123,VENTES!H124,VENTES!H125) -> 1161.28 | V3: =SUM(B3,E3,H3,K3,N3,Q3,T3) -> 35803.036 | W3: =SUM(C3,F3,I3,O3,R3,U3) -> 10940.126
A4: Ventes par heure | B4: =B3/B2 -> 331.31574 | C4: =C3/C2 -> 441.1655 | E4: =E3/E2 -> 108.99057 | F4: =F3/F2 -> 176.16941 | H4: =H3/H2 -> 182.50388 | I4: =I3/I2 -> #DIV/0! | K4: =K3/K2 -> 242.82284 | L4: =L3/L2 -> 330.38833 | N4: =N3/N2 -> 97.734545 | O4: =O3/O2 -> 88.035 | Q4: =Q3/Q2 -> 98.857005 | R4: =R3/R2 -> 65.475 | T4: =T3/T2 -> 89.329231 | U4: =U3/U2 -> 89.329231 | V4: =V3/V2 -> 168.88224 | W4: =W3/W2 -> 176.45365
A5: Nb de ventes | B5: 21 | C5: 10 | E5: 12 | F5: 8 | H5: 13 | I5: 0 | K5: 18 | L5: 8 | N5: 13 | O5: 5 | Q5: 22 | R5: 4 | U5: 4 | W5: =SUM(C5,F5,I5,O5,R5,U5) -> 31
A6: Vente/heure | B6: =B5/B2 -> 0.55263158 | C6: =8/9 -> 0.88888889 | E6: =E5/E2 -> 0.23529412 | F6: =F5/F2 -> 0.47058824 | H6: =H5/H2 -> 0.61904762 | I6: =I5/I2 -> #DIV/0! | K6: =K5/K2 -> 0.66666667 | L6: =L5/L2 -> 0.66666667 | N6: =N5/N2 -> 0.59090909 | Q6: =Q5/Q2 -> 0.55 | R6: =R5/R2 -> 0.33333333 | U6: =U5/U2 -> 0.30769231 | V6: =AVERAGE(B6,E6,H6,K6,N6) -> 0.53290981 | W6: =W5/W2 -> 0.5
A7: Refus | B7: 20
A8: Estimé booked | C8: 1
A9: Upsell | B9: =SUM(VENTES!J4,VENTES!J5,VENTES!J8) -> 501.91 | C9: 0 | Q9: 195 | V9: =SUM(B9,E9,H9,K9,N9,Q9) -> 696.91
A10: Upsell par heure | B10: =B9/B2 -> 13.208158 | C10: 0 | Q10: =Q9/Q2 -> 4.875 | V10: =SUM(B10,E10,H10,K10,N10,Q10) -> 18.083158
A11: Appels | B11: 173 | C11: 102 | E11: 149 | H11: 87 | I11: 0 | K11: 122 | N11: 123 | O11: 0 | Q11: 36 | V11: =SUM(B11,E11,H11,K11,N11,Q11) -> 690
A12: Appels par heure | B12: =B11/B2 -> 4.5526316 | C12: =C11/C2 -> 8.5 | E12: =E11/E2 -> 2.9215686 | H12: =H11/H2 -> 4.1428571 | I12: =I11/I2 -> #DIV/0! | K12: =K11/K2 -> 4.5185185 | L12: =L11/L2 -> 0 | N12: =N11/N2 -> 5.5909091 | O12: =O11/O2 -> 0 | Q12: =Q11/Q2 -> 0.9 | V12: =V11/V2 -> 3.254717
V13: =SUM(B13,E13,H13,K13,N13,Q13) -> 0
V14: =SUM(B14,E14,H14,K14,N14,Q14) -> 0
V15: =SUM(B15,E15,H15,K15,N15,Q15) -> 0
V16: =SUM(B16,E16,H16,K16,N16,Q16) -> 0
